Workbook

Sheet Summary
A4: SUMMARY OF EXPENSE CLAIM-BACK FOR ZOTT
A5: Period: | C5: 01/03/2026-31/03/2026
A7: No | B7: Platform | C7: Expense | D7: Claimback Details | E7: Total (exclude VAT) | F7: % VAT | G7: VAT Fee | H7: Grand total
A8: 1 | B8: TIKTOK | D8: Subsidy | E8: =-SUMIF(Defaut!G:G,"tiktok",Defaut!AF:AF) -> 124074.07 | F8: 0.1 | G8: =ROUND(E8*F8,0) -> 12407 | H8: =G8+E8 -> 136481.07
A9: 2 | B9: LAZADA | D9: Subsidy | E9: =-SUMIF(Defaut!G:G,"lazada",Defaut!AF:AF) -> 79629.639 | F9: 0.1 | G9: =ROUND(E9*F9,0) -> 7963 | H9: =G9+E9 -> 87592.639
A10: 3 | B10: SHOPEE | D10: Subsidy | E10: =-SUMIF(Defaut!G:G,"shopee_v2",Defaut!AF:AF) -> 26888712 | F10: 0.1 | G10: =ROUND(E10*F10,0) -> 2688871 | H10: =G10+E10 -> 29577583
A11: Phí vận hành gian hàng | E11: 35000000 | F11: 0.1 | G11: =ROUNDDOWN(E11*F11,0) -> 3500000 | H11: =G11+E11 -> 38500000
A12: Total value (exclude VAT) | E12: =SUBTOTAL(9,E8:E11) -> 62092416
A13: Thuế GTGT ( VAT) | E13: =SUBTOTAL(9,G8:G11) -> 6209241
A14: Total value (include VAT) | E14: =SUBTOTAL(9,H8:H11) -> 68301657

Sheet Defaut
S1: =SUM(S2:S1048576) -> 182490000 | U1: =SUM(U2:U1048576) -> 26135001 | Z1: =SUM(Z2:Z1048576) -> 1.53606e+08 | AB1: =SUM(AB2:AB1048576) -> 1.53606e+08 | AF1: =SUM(AF2:AF1048576) -> -27092416 | AG1: =SUM(AG2:AG1048576) -> -29801658
A2: Thời gian tạo | B2: Thời gian vận đơn được tạo | C2: Thời gian đóng gói hoàn thành | D2: Thời gian bàn giao | E2: Thời gian hoàn thành | F2: Thời gian đối soát | G2: Nền tảng | H2: Loại sản phẩm | I2: sku | J2: Tên sản phẩm | K2: Đơn vị xử lý đơn hàng (fulfill) | L2: Tiền tệ | M2: Trạng thái | N2: Mã đơn hàng Omisell | O2: Mã đơn hàng | P2: Trọng lượng | Q2: Thể tích | R2: Số lượng | S2: Số tiền hàng hoá | T2: Doanh thu | U2: Mã giảm giá từ người bán | V2: Giảm giá từ người bán | W2: Mã giảm giá từ nền tảng | X2: Giảm giá từ nền tảng | Y2: Giảm giá khác | Z2: NMV | AA2: Thuế GTGT | AB2: Revenue | AC2: Claim back | AD2: GAP | AE2: Vat | AF2: Subsidy (-VAT) | AG2: Subsidy (+VAT) | AH2: Note
A3: 2026-03-31 12:24:33 | B3: 2026-03-31 12:25:38 | C3: 2026-03-31 13:33:07 | D3: 2026-03-31 14:09:43 | E3: 2026-03-31 14:27:02 | F3: 2026-03-31 17:52:04 | G3: shopee_v2 | H3: physical | I3: MON055GH04VAN | J3: Váng sữa Zott Monte vị Vani nhập khẩu từ ĐỨC, bé 6 tháng tuổi trở lên (vỉ - 55g x 4 hũ) từ Sữa tươi, KHÔNG chất bảo quản | K3: merchant | L3: VND | M3: Giao hàng thành công | N3: ODVN2603318F7BC33D | O3: 260331JEART4VD | P3: 220 | R3: 2 | S3: 150000 | T3: 160000 | U3: 20000 | V3: 16000 | W3: 0 | X3: 44800 | Y3: 0 | Z3: 124000 | AA3: 8 | AB3: =Z3 -> 124000 | AC3: =IF(AB3-S3<0,"YES","NO") -> YES | AD3: =IF(AC3="NO",0,AB3-S3) -> -26000 | AE3: 0.08 | AF3: =AD3/(1+AE3) -> -24074.074 | AG3: =AF3*1.1 -> -26481.481
A4: 2026-03-31 10:20:42 | B4: 2026-03-31 10:26:08 | C4: 2026-03-31 10:28:56 | D4: 2026-03-31 11:05:47 | E4: 2026-03-31 11:13:59 | F4: 2026-03-31 11:14:48 | G4: shopee_v2 | H4: gift | I4: GIFT-YEMANDAM | J4: [HÀNG TẶNG KHÔNG BÁN] Yếm ăn dặm cho bé | K4: merchant | L4: VND | M4: Giao hàng thành công | N4: ODVN2603310C876F2B | O4: 260331J7DCVUWV | P4: 100 | Q4: 5x2x5 | R4: 1 | S4: 0 | T4: 0 | U4: 0 | V4: 0 | W4: 0 | X4: 0 | Y4: 0 | Z4: 0 | AA4: 8 | AB4: =Z4 -> 0 | AC4: =IF(AB4-S4<0,"YES","NO") -> NO | AD4: =IF(AC4="NO",0,AB4-S4) -> 0 | AE4: 0.08 | AF4: =AD4/(1+AE4) -> 0 | AG4: =AF4*1.1 -> 0
A5: 2026-03-31 10:20:42 | B5: 2026-03-31 10:26:08 | C5: 2026-03-31 10:28:56 | D5: 2026-03-31 11:05:47 | E5: 2026-03-31 11:13:59 | F5: 2026-03-31 11:14:48 | G5: shopee_v2 | H5: physical | I5: MON055GH04VAN | J5: Váng sữa Zott Monte vị Vani nhập khẩu từ ĐỨC, bé 6 tháng tuổi trở lên (vỉ - 55g x 4 hũ) từ Sữa tươi, KHÔNG chất bảo quản | K5: merchant | L5: VND | M5: Giao hàng thành công | N5: ODVN2603310C876F2B | O5: 260331J7DCVUWV | P5: 220 | R5: 4 | S5: 300000 | T5: 320000 | U5: 20000 | V5: 32000 | W5: 0 | X5: 65561 | Y5: 0 | Z5: 268000 | AA5: 8 | AB5: =Z5 -> 268000 | AC5: =IF(AB5-S5<0,"YES","NO") -> YES | AD5: =IF(AC5="NO",0,AB5-S5) -> -32000 | AE5: 0.08 | AF5: =AD5/(1+AE5) -> -29629.63 | AG5: =AF5*1.1 -> -32592.593
A6: 2026-03-30 22:48:52 | B6: 2026-03-30 22:54:18 | C6: 2026-03-31 09:10:06 | D6: 2026-03-31 09:25:25 | E6: 2026-03-31 10:33:32 | F6: 2026-03-31 10:47:26 | G6: shopee_v2 | H6: gift | I6: GIFT-YEMANDAM | J6: [HÀNG TẶNG KHÔNG BÁN] Yếm ăn dặm cho bé | K6: merchant | L6: VND | M6: Giao hàng thành công | N6: ODVN260330E5965C46 | O6: 260330H0R9XA8V | P6: 100 | Q6: 5x2x5 | R6: 1 | S6: 0 | T6: 0 | U6: 0 | V6: 0 | W6: 0 | X6: 0 | Y6: 0 | Z6: 0 | AA6: 8 | AB6: =Z6 -> 0 | AC6: =IF(AB6-S6<0,"YES","NO") -> NO | AD6: =IF(AC6="NO",0,AB6-S6) -> 0 | AE6: 0.08 | AF6: =AD6/(1+AE6) -> 0 | AG6: =AF6*1.1 -> 0
A7: 2026-03-30 22:48:52 | B7: 2026-03-30 22:54:18 | C7: 2026-03-31 09:10:06 | D7: 2026-03-31 09:25:25 | E7: 2026-03-31 10:33:32 | F7: 2026-03-31 10:47:26 | G7: shopee_v2 | H7: physical | I7: MON055GH04VAN | J7: Váng sữa Zott Monte vị Vani nhập khẩu từ ĐỨC, bé 6 tháng tuổi trở lên (vỉ - 55g x 4 hũ) từ Sữa tươi, KHÔNG chất bảo quản | K7: merchant | L7: VND | M7: Giao hàng thành công | N7: ODVN260330E5965C46 | O7: 260330H0R9XA8V | P7: 220 | R7: 6 | S7: 450000 | T7: 480000 | U7: 75000 | V7: 48000 | W7: 0 | X7: 135690 | Y7: 0 | Z7: 357000 | AA7: 8 | AB7: =Z7 -> 357000 | AC7: =IF(AB7-S7<0,"YES","NO") -> YES | AD7: =IF(AC7="NO",0,AB7-S7) -> -93000 | AE7: 0.08 | AF7: =AD7/(1+AE7) -> -86111.111 | AG7: =AF7*1.1 -> -94722.222
A8: 2026-03-30 18:45:59 | B8: 2026-03-30 22:51:13 | C8: 2026-03-31 09:04:31 | D8: 2026-03-31 10:26:21 | E8: 2026-03-31 10:44:55 | F8: 2026-03-31 21:54:20 | G8: shopee_v2 | H8: physical | I8: MON055GH04VAN | J8: Váng sữa Zott Monte vị Vani nhập khẩu từ ĐỨC, bé 6 tháng tuổi trở lên (vỉ - 55g x 4 hũ) từ Sữa tươi, KHÔNG chất bảo quản | K8: merchant | L8: VND | M8: Giao hàng thành công | N8: ODVN260330B4B89123 | O8: 260330GK601BKA | P8: 220 | R8: 2 | S8: 150000 | T8: 160000 | U8: 20000 | V8: 16000 | W8: 0 | X8: 44800 | Y8: 0 | Z8: 124000 | AA8: 8 | AB8: =Z8 -> 124000 | AC8: =IF(AB8-S8<0,"YES","NO") -> YES | AD8: =IF(AC8="NO",0,AB8-S8) -> -26000 | AE8: 0.08 | AF8: =AD8/(1+AE8) -> -24074.074 | AG8: =AF8*1.1 -> -26481.481
A9: 2026-03-30 11:52:51 | B9: 2026-03-30 12:45:40 | C9: 2026-03-30 13:39:09 | D9: 2026-03-30 15:17:21 | E9: 2026-03-30 16:25:41 | F9: 2026-03-31 09:35:35 | G9: shopee_v2 | H9: gift | I9: GIFT-YEMANDAM | J9: [HÀNG TẶNG KHÔNG BÁN] Yếm ăn dặm cho bé | K9: merchant | L9: VND | M9: Giao hàng thành công | N9: ODVN2603309EB51C35 | O9: 260330FV398093 | P9: 100 | Q9: 5x2x5 | R9: 1 | S9: 0 | T9: 0 | U9: 0 | V9: 0 | W9: 0 | X9: 0 | Y9: 0 | Z9: 0 | AA9: 8 | AB9: =Z9 -> 0 | AC9: =IF(AB9-S9<0,"YES","NO") -> NO | AD9: =IF(AC9="NO",0,AB9-S9) -> 0 | AE9: 0.08 | AF9: =AD9/(1+AE9) -> 0 | AG9: =AF9*1.1 -> 0
A10: 2026-03-30 11:52:51 | B10: 2026-03-30 12:45:40 | C10: 2026-03-30 13:39:09 | D10: 2026-03-30 15:17:21 | E10: 2026-03-30 16:25:41 | F10: 2026-03-31 09:35:35 | G10: shopee_v2 | H10: physical | I10: MNF055GC04VAN | J10: [Giao Hỏa Tốc] Phô mai tươi Montinis vị Vani nhập ĐỨC (vỉ - 55g x 4 hũ) | K10: merchant | L10: VND | M10: Giao hàng thành công | N10: ODVN2603309EB51C35 | O10: 260330FV398093 | P10: 220 | Q10: 10x10x15 | R10: 6 | S10: 354000 | T10: 420000 | U10: 75000 | V10: 37000.02 | W10: 0 | X10: 124999.98 | Y10: 0 | Z10: 307999.98 | AA10: 8 | AB10: =Z10 -> 307999.98 | AC10: =IF(AB10-S10<0,"YES","NO") -> YES | AD10: =IF(AC10="NO",0,AB10-S10) -> -46000.02 | AE10: 0.08 | AF10: =AD10/(1+AE10) -> -42592.611 | AG10: =AF10*1.1 -> -46851.872
A11: 2026-03-30 11:27:57 | B11: 2026-03-30 11:29:30 | C11: 2026-03-30 13:48:51 | D11: 2026-03-30 14:08:14 | E11: 2026-03-30 14:30:51 | F11: 2026-03-30 15:27:26 | G11: shopee_v2 | H11: gift | I11: GIFT-TAPDEGMS | J11: [HÀNG TẶNG KHÔNG BÁN] Tạp dề vào bếp xinh xắn Zott Gourmet Slices (màu ngẫu nhiên) | K11: merchant | L11: VND | M11: Giao hàng thành công | N11: ODVN26033069A3FF7C | O11: 260330FTPRGQR6 | P11: 20 | Q11: 5x2x5 | R11: 1 | S11: 0 | T11: 0 | U11: 0 | V11: 0 | W11: 0 | X11: 0 | Y11: 0 | Z11: 0 | AA11: 8 | AB11: =Z11 -> 0 | AC11: =IF(AB11-S11<0,"YES","NO") -> NO | AD11: =IF(AC11="NO",0,AB11-S11) -> 0 | AE11: 0.08 | AF11: =AD11/(1+AE11) -> 0 | AG11: =AF11*1.1 -> 0
A12: 2026-03-30 11:27:57 | B12: 2026-03-30 11:29:30 | C12: 2026-03-30 13:48:51 | D12: 2026-03-30 14:08:14 | E12: 2026-03-30 14:30:51 | F12: 2026-03-30 15:27:26 | G12: shopee_v2 | H12: physical | I12: GMS200GL12SDW | J12: Phô mai lát Zott Gourmet Slices SANDWICH nhập khẩu từ Đức, phù hợp cả gia đình (1 gói 200g – 12 lát), làm từ Sữa tươi giàu Canxi, Chất đạm | K12: merchant | L12: VND | M12: Giao hàng thành công | N12: ODVN26033069A3FF7C | O12: 260330FTPRGQR6 | P12: 200 | R12: 6 | S12: 432000 | T12: 480000 | U12: 75000 | V12: 48000 | W12: 0 | X12: 132120 | Y12: 0 | Z12: 357000 | AA12: 8 | AB12: =Z12 -> 357000 | AC12: =IF(AB12-S12<0,"YES","NO") -> YES | AD12: =IF(AC12="NO",0,AB12-S12) -> -75000 | AE12: 0.08 | AF12: =AD12/(1+AE12) -> -69444.444 | AG12: =AF12*1.1 -> -76388.889
A13: 2026-03-30 09:33:37 | B13: 2026-03-30 09:37:01 | C13: 2026-03-30 09:37:40 | D13: 2026-03-30 10:40:20 | E13: 2026-03-30 12:22:25 | F13: 2026-03-31 09:39:09 | G13: shopee_v2 | H13: gift | I13: GIFT-YEMANDAM | J13: [HÀNG TẶNG KHÔNG BÁN] Yếm ăn dặm cho bé | K13: merchant | L13: VND | M13: Giao hàng thành công | N13: ODVN260330FDE0969B | O13: 260330FMA99BAT | P13: 100 | Q13: 5x2x5 | R13: 1 | S13: 0 | T13: 0 | U13: 0 | V13: 0 | W13: 0 | X13: 0 | Y13: 0 | Z13: 0 | AA13: 8 | AB13: =Z13 -> 0 | AC13: =IF(AB13-S13<0,"YES","NO") -> NO | AD13: =IF(AC13="NO",0,AB13-S13) -> 0 | AE13: 0.08 | AF13: =AD13/(1+AE13) -> 0 | AG13: =AF13*1.1 -> 0
A14: 2026-03-30 09:33:37 | B14: 2026-03-30 09:37:01 | C14: 2026-03-30 09:37:40 | D14: 2026-03-30 10:40:20 | E14: 2026-03-30 12:22:25 | F14: 2026-03-31 09:39:09 | G14: shopee_v2 | H14: physical | I14: MON055GH04VAN | J14: Váng sữa Zott Monte vị Vani nhập khẩu từ ĐỨC, bé 6 tháng tuổi trở lên (vỉ - 55g x 4 hũ) từ Sữa tươi, KHÔNG chất bảo quản | K14: merchant | L14: VND | M14: Giao hàng thành công | N14: ODVN260330FDE0969B | O14: 260330FMA99BAT | P14: 220 | R14: 3 | S14: 225000 | T14: 240000 | U14: 35000.01 | V14: 24000 | W14: 0 | X14: 62150.01 | Y14: 0 | Z14: 180999.99 | AA14: 8 | AB14: =Z14 -> 180999.99 | AC14: =IF(AB14-S14<0,"YES","NO") -> YES | AD14: =IF(AC14="NO",0,AB14-S14) -> -44000.01 | AE14: 0.08 | AF14: =AD14/(1+AE14) -> -40740.75 | AG14: =AF14*1.1 -> -44814.825
A15: 2026-03-30 08:53:11 | B15: 2026-03-30 08:54:22 | C15: 2026-03-30 09:03:58 | D15: 2026-03-30 09:34:49 | E15: 2026-03-30 10:25:10 | F15: 2026-03-31 09:30:46 | G15: shopee_v2 | H15: physical | I15: MON055GH04CXP | J15: [Giao nhanh 2H] Váng sữa Zott Monte Canxi Plus nhập khẩu từ ĐỨC, bé 6 tháng tuổi trở lên (vỉ - 55g x 4 hũ) từ Sữa tươi, KHÔNG chất bảo quản | K15: merchant | L15: VND | M15: Giao hàng thành công | N15: ODVN260330CB3F03A4 | O15: 260330FJ1YQG72 | P15: 220 | R15: 2 | S15: 150000 | T15: 160000 | U15: 20000 | V15: 10000 | W15: 0 | X15: 33000 | Y15: 0 | Z15: 130000 | AA15: 8 | AB15: =Z15 -> 130000 | AC15: =IF(AB15-S15<0,"YES","NO") -> YES | AD15: =IF(AC15="NO",0,AB15-S15) -> -20000 | AE15: 0.08 | AF15: =AD15/(1+AE15) -> -18518.519 | AG15: =AF15*1.1 -> -20370.37
A16: 2026-03-30 07:46:47 | B16: 2026-03-30 07:52:02 | C16: 2026-03-30 08:54:41 | D16: 2026-03-30 09:12:14 | E16: 2026-03-30 09:58:51 | F16: 2026-03-31 20:36:04 | G16: shopee_v2 | H16: physical | I16: MON055GH04VAN | J16: Váng sữa Zott Monte vị Vani nhập khẩu từ ĐỨC, bé 6 tháng tuổi trở lên (vỉ - 55g x 4 hũ) từ Sữa tươi, KHÔNG chất bảo quản | K16: merchant | L16: VND | M16: Giao hàng thành công | N16: ODVN260330352D95CB | O16: 260330FEB87NYJ | P16: 220 | R16: 3 | S16: 225000 | T16: 240000 | U16: 35000.01 | V16: 24000 | W16: 0 | X16: 71199.99 | Y16: 0 | Z16: 180999.99 | AA16: 8 | AB16: =Z16 -> 180999.99 | AC16: =IF(AB16-S16<0,"YES","NO") -> YES | AD16: =IF(AC16="NO",0,AB16-S16) -> -44000.01 | AE16: 0.08 | AF16: =AD16/(1+AE16) -> -40740.75 | AG16: =AF16*1.1 -> -44814.825
A17: 2026-03-29 22:42:48 | B17: 2026-03-29 22:48:10 | C17: 2026-03-30 08:54:30 | D17: 2026-03-30 09:47:04 | E17: 2026-03-30 10:22:09 | F17: 2026-03-30 23:50:06 | G17: shopee_v2 | H17: physical | I17: MON055GH04VAN | J17: Váng sữa Zott Monte vị Vani nhập khẩu từ ĐỨC, bé 6 tháng tuổi trở lên (vỉ - 55g x 4 hũ) từ Sữa tươi, KHÔNG chất bảo quản | K17: merchant | L17: VND | M17: Giao hàng thành công | N17: ODVN260329DC12470A | O17: 260329EFXJ7M2E | P17: 220 | R17: 2 | S17: 150000 | T17: 160000 | U17: 20000 | V17: 16000 | W17: 0 | X17: 44800 | Y17: 0 | Z17: 124000 | AA17: 8 | AB17: =Z17 -> 124000 | AC17: =IF(AB17-S17<0,"YES","NO") -> YES | AD17: =IF(AC17="NO",0,AB17-S17) -> -26000 | AE17: 0.08 | AF17: =AD17/(1+AE17) -> -24074.074 | AG17: =AF17*1.1 -> -26481.481
A18: 2026-03-28 23:10:48 | B18: 2026-03-28 23:16:22 | C18: 2026-03-30 08:53:42 | D18: 2026-03-30 09:23:16 | E18: 2026-03-30 10:07:23 | F18: 2026-03-30 10:55:10 | G18: shopee_v2 | H18: physical | I18: MON055GH04VAN | J18: Váng sữa Zott Monte vị Vani nhập khẩu từ ĐỨC, bé 6 tháng tuổi trở lên (vỉ - 55g x 4 hũ) từ Sữa tươi, KHÔNG chất bảo quản | K18: merchant | L18: VND | M18: Giao hàng thành công | N18: ODVN26032888FDD9AA | O18: 260329C112YQ1G | P18: 220 | R18: 6 | S18: 450000 | T18: 480000 | U18: 75000 | V18: 48000 | W18: 0 | X18: 139260 | Y18: 0 | Z18: 357000 | AA18: 8 | AB18: =Z18 -> 357000 | AC18: =IF(AB18-S18<0,"YES","NO") -> YES | AD18: =IF(AC18="NO",0,AB18-S18) -> -93000 | AE18: 0.08 | AF18: =AD18/(1+AE18) -> -86111.111 | AG18: =AF18*1.1 -> -94722.222
A19: 2026-03-27 23:43:48 | B19: 2026-03-27 23:50:58 | C19: 2026-03-28 07:51:39 | D19: 2026-03-28 08:55:19 | E19: 2026-03-28 09:51:36 | F19: 2026-03-28 15:48:44 | G19: shopee_v2 | H19: physical | I19: MNS055GC04PLN | J19: [Giao Hoả Tốc] Sữa chua Montinis vị Nguyên bản nhập Đức (vỉ - 55g x 4 hũ) | K19: merchant | L19: VND | M19: Giao hàng thành công | N19: ODVN260327806DF183 | O19: 2603289JDNY4D7 | P19: 220 | Q19: 13x5x13 | R19: 3 | S19: 177000 | T19: 195000 | U19: 35000.01 | V19: 19500 | W19: 0 | X19: 63099.99 | Y19: 0 | Z19: 140499.99 | AA19: 8 | AB19: =Z19 -> 140499.99 | AC19: =IF(AB19-S19<0,"YES","NO") -> YES | AD19: =IF(AC19="NO",0,AB19-S19) -> -36500.01 | AE19: 0.08 | AF19: =AD19/(1+AE19) -> -33796.306 | AG19: =AF19*1.1 -> -37175.936
A20: 2026-03-27 21:46:44 | B20: 2026-03-27 22:03:40 | C20: 2026-03-28 10:24:19 | D20: 2026-03-28 10:34:55 | E20: 2026-03-28 11:40:02 | F20: 2026-03-28 15:12:15 | G20: shopee_v2 | H20: gift | I20: GIFT-TAPDEGMS | J20: [HÀNG TẶNG KHÔNG BÁN] Tạp dề vào bếp xinh xắn Zott Gourmet Slices (màu ngẫu nhiên) | K20: merchant | L20: VND | M20: Giao hàng thành công | N20: ODVN2603271FA1F4BD | O20: 2603279BVF6W9A | P20: 20 | Q20: 5x2x5 | R20: 1 | S20: 0 | T20: 0 | U20: 0 | V20: 0 | W20: 0 | X20: 0 | Y20: 0 | Z20: 0 | AA20: 8 | AB20: =Z20 -> 0 | AC20: =IF(AB20-S20<0,"YES","NO") -> NO | AD20: =IF(AC20="NO",0,AB20-S20) -> 0 | AE20: 0.08 | AF20: =AD20/(1+AE20) -> 0 | AG20: =AF20*1.1 -> 0
A21: 2026-03-27 21:46:44 | B21: 2026-03-27 22:03:40 | C21: 2026-03-28 10:24:19 | D21: 2026-03-28 10:34:55 | E21: 2026-03-28 11:40:02 | F21: 2026-03-28 15:12:15 | G21: shopee_v2 | H21: physical | I21: GMS200GL12SDW | J21: Phô mai lát Zott Gourmet Slices SANDWICH nhập khẩu từ Đức, phù hợp cả gia đình (1 gói 200g – 12 lát), làm từ Sữa tươi giàu Canxi, Chất đạm | K21: merchant | L21: VND | M21: Giao hàng thành công | N21: ODVN2603271FA1F4BD | O21: 2603279BVF6W9A | P21: 200 | R21: 6 | S21: 432000 | T21: 480000 | U21: 75000 | V21: 48000 | W21: 0 | X21: 135690 | Y21: 0 | Z21: 357000 | AA21: 8 | AB21: =Z21 -> 357000 | AC21: =IF(AB21-S21<0,"YES","NO") -> YES | AD21: =IF(AC21="NO",0,AB21-S21) -> -75000 | AE21: 0.08 | AF21: =AD21/(1+AE21) -> -69444.444 | AG21: =AF21*1.1 -> -76388.889
A22: 2026-03-27 21:35:46 | B22: 2026-03-27 21:48:42 | C22: 2026-03-28 08:39:47 | D22: 2026-03-28 09:18:58 | E22: 2026-03-28 10:02:12 | F22: 2026-03-28 21:58:01 | G22: shopee_v2 | H22: physical | I22: MON055GH04VAN | J22: Váng sữa Zott Monte vị Vani nhập khẩu từ ĐỨC, bé 6 tháng tuổi trở lên (vỉ - 55g x 4 hũ) từ Sữa tươi, KHÔNG chất bảo quản | K22: merchant | L22: VND | M22: Giao hàng thành công | N22: ODVN260327BCB906DF | O22: 2603279B8QU1RU | P22: 220 | R22: 6 | S22: 450000 | T22: 480000 | U22: 75000 | V22: 48000 | W22: 0 | X22: 164250 | Y22: 0 | Z22: 357000 | AA22: 8 | AB22: =Z22 -> 357000 | AC22: =IF(AB22-S22<0,"YES","NO") -> YES | AD22: =IF(AC22="NO",0,AB22-S22) -> -93000 | AE22: 0.08 | AF22: =AD22/(1+AE22) -> -86111.111 | AG22: =AF22*1.1 -> -94722.222
A23: 2026-03-27 14:54:36 | B23: 2026-03-27 14:57:39 | C23: 2026-03-27 15:32:31 | D23: 2026-03-27 15:50:41 | E23: 2026-03-27 16:31:53 | F23: 2026-03-30 17:43:25 | G23: shopee_v2 | H23: physical | I23: MON055GH04VAN | J23: Váng sữa Zott Monte vị Vani nhập khẩu từ ĐỨC, bé 6 tháng tuổi trở lên (vỉ - 55g x 4 hũ) từ Sữa tươi, KHÔNG chất bảo quản | K23: merchant | L23: VND | M23: Giao hàng thành công | N23: ODVN260327B119C04F | O23: 2603278MUGQYXR | P23: 220 | R23: 6 | S23: 450000 | T23: 480000 | U23: 75000 | V23: 48000 | W23: 0 | X23: 132120 | Y23: 0 | Z23: 357000 | AA23: 8 | AB23: =Z23 -> 357000 | AC23: =IF(AB23-S23<0,"YES","NO") -> YES | AD23: =IF(AC23="NO",0,AB23-S23) -> -93000 | AE23: 0.08 | AF23: =AD23/(1+AE23) -> -86111.111 | AG23: =AF23*1.1 -> -94722.222
A24: 2026-03-27 14:27:38 | B24: 2026-03-27 14:28:46 | C24: 2026-03-27 15:32:26 | D24: 2026-03-27 16:02:06 | E24: 2026-03-27 16:21:18 | F24: 2026-03-30 17:30:37 | G24: shopee_v2 | H24: gift | I24: GIFT-BOBONGRO | J24: [HÀNG TẶNG KHÔNG BÁN] Bộ đồ chơi bóng rổ đáng yêu (hình ngẫu nhiên) | K24: merchant | L24: VND | M24: Giao hàng thành công | N24: ODVN2603278A7E2EC8 | O24: 2603278KB9PRRF | P24: 20000 | Q24: 5x3x5 | R24: 1 | S24: 0 | T24: 0 | U24: 0 | V24: 0 | W24: 0 | X24: 0 | Y24: 0 | Z24: 0 | AA24: 8 | AB24: =Z24 -> 0 | AC24: =IF(AB24-S24<0,"YES","NO") -> NO | AD24: =IF(AC24="NO",0,AB24-S24) -> 0 | AE24: 0.08 | AF24: =AD24/(1+AE24) -> 0 | AG24: =AF24*1.1 -> 0
A25: 2026-03-27 14:27:38 | B25: 2026-03-27 14:28:46 | C25: 2026-03-27 15:32:26 | D25: 2026-03-27 16:02:06 | E25: 2026-03-27 16:21:18 | F25: 2026-03-30 17:30:37 | G25: shopee_v2 | H25: physical | I25: MNS055GC04MNG | J25: [Giao Hoả Tốc] Sữa chua Montinis vị Xoài nhập Đức (vỉ - 55g x 4 hũ) | K25: merchant | L25: VND | M25: Giao hàng thành công | N25: ODVN2603278A7E2EC8 | O25: 2603278KB9PRRF | P25: 220 | Q25: 13x5x13 | R25: 3 | S25: 177000 | T25: 195000 | U25: 35000.01 | V25: 19500 | W25: 0 | X25: 63099.99 | Y25: 0 | Z25: 140499.99 | AA25: 8 | AB25: =Z25 -> 140499.99 | AC25: =IF(AB25-S25<0,"YES","NO") -> YES | AD25: =IF(AC25="NO",0,AB25-S25) -> -36500.01 | AE25: 0.08 | AF25: =AD25/(1+AE25) -> -33796.306 | AG25: =AF25*1.1 -> -37175.936
A26: 2026-03-27 14:18:48 | B26: 2026-03-27 14:24:16 | C26: 2026-03-27 15:32:13 | D26: 2026-03-27 15:41:36 | E26: 2026-03-27 16:10:35 | F26: 2026-03-30 17:14:59 | G26: shopee_v2 | H26: physical | I26: MON055GH04VAN | J26: Váng sữa Zott Monte vị Vani nhập khẩu từ ĐỨC, bé 6 tháng tuổi trở lên (vỉ - 55g x 4 hũ) từ Sữa tươi, KHÔNG chất bảo quản | K26: merchant | L26: VND | M26: Giao hàng thành công | N26: ODVN2603272860DA52 | O26: 2603278JUG6HAD | P26: 220 | R26: 6 | S26: 450000 | T26: 480000 | U26: 79999.98 | V26: 48000 | W26: 0 | X26: 143359.98 | Y26: 0 | Z26: 352000.02 | AA26: 8 | AB26: =Z26 -> 352000.02 | AC26: =IF(AB26-S26<0,"YES","NO") -> YES | AD26: =IF(AC26="NO",0,AB26-S26) -> -97999.98 | AE26: 0.08 | AF26: =AD26/(1+AE26) -> -90740.722 | AG26: =AF26*1.1 -> -99814.794
A27: 2026-03-27 14:17:31 | B27: 2026-03-27 14:24:22 | C27: 2026-03-27 15:32:20 | D27: 2026-03-27 15:41:40 | E27: 2026-03-27 15:48:03 | F27: 2026-03-30 16:15:21 | G27: shopee_v2 | H27: physical | I27: MON055GH04VAN | J27: Váng sữa Zott Monte vị Vani nhập khẩu từ ĐỨC, bé 6 tháng tuổi trở lên (vỉ - 55g x 4 hũ) từ Sữa tươi, KHÔNG chất bảo quản | K27: merchant | L27: VND | M27: Giao hàng thành công | N27: ODVN2603271D5502AB | O27: 2603278JS6TBGW | P27: 220 | R27: 3 | S27: 225000 | T27: 240000 | U27: 35000.01 | V27: 24000 | W27: 0 | X27: 71199.99 | Y27: 0 | Z27: 180999.99 | AA27: 8 | AB27: =Z27 -> 180999.99 | AC27: =IF(AB27-S27<0,"YES","NO") -> YES | AD27: =IF(AC27="NO",0,AB27-S27) -> -44000.01 | AE27: 0.08 | AF27: =AD27/(1+AE27) -> -40740.75 | AG27: =AF27*1.1 -> -44814.825
A28: 2026-03-27 14:12:10 | B28: 2026-03-27 14:17:33 | C28: 2026-03-27 15:32:07 | D28: 2026-03-27 15:55:31 | E28: 2026-03-27 16:25:40 | F28: 2026-03-28 22:36:06 | G28: shopee_v2 | H28: gift | I28: GIFT-YEMANDAM | J28: [HÀNG TẶNG KHÔNG BÁN] Yếm ăn dặm cho bé | K28: merchant | L28: VND | M28: Giao hàng thành công | N28: ODVN260327D50C357E | O28: 2603278JFKP8A8 | P28: 100 | Q28: 5x2x5 | R28: 1 | S28: 0 | T28: 0 | U28: 0 | V28: 0 | W28: 0 | X28: 0 | Y28: 0 | Z28: 0 | AA28: 8 | AB28: =Z28 -> 0 | AC28: =IF(AB28-S28<0,"YES","NO") -> NO | AD28: =IF(AC28="NO",0,AB28-S28) -> 0 | AE28: 0.08 | AF28: =AD28/(1+AE28) -> 0 | AG28: =AF28*1.1 -> 0
A29: 2026-03-27 14:12:10 | B29: 2026-03-27 14:17:33 | C29: 2026-03-27 15:32:07 | D29: 2026-03-27 15:55:31 | E29: 2026-03-27 16:25:40 | F29: 2026-03-28 22:36:06 | G29: shopee_v2 | H29: physical | I29: MON055GH04CLA | J29: Váng sữa Zott Monte vị Classic nhập khẩu từ ĐỨC, bé 6 tháng tuổi trở lên (vỉ - 55g x 4 hũ) từ Sữa tươi, KHÔNG chất bảo quản | K29: merchant | L29: VND | M29: Giao hàng thành công | N29: ODVN260327D50C357E | O29: 2603278JFKP8A8 | P29: 220 | R29: 6 | S29: 450000 | T29: 480000 | U29: 75000 | V29: 49000.02 | W29: 0 | X29: 139080 | Y29: 0 | Z29: 355999.98 | AA29: 8 | AB29: =Z29 -> 355999.98 | AC29: =IF(AB29-S29<0,"YES","NO") -> YES | AD29: =IF(AC29="NO",0,AB29-S29) -> -94000.02 | AE29: 0.08 | AF29: =AD29/(1+AE29) -> -87037.056 | AG29: =AF29*1.1 -> -95740.761
A30: 2026-03-27 12:01:29 | B30: 2026-03-27 12:09:22 | C30: 2026-03-27 14:07:37 | D30: 2026-03-27 14:17:30 | E30: 2026-03-27 14:47:40 | F30: 2026-03-28 10:33:34 | G30: shopee_v2 | H30: gift | I30: GIFT-YEMANDAM | J30: [HÀNG TẶNG KHÔNG BÁN] Yếm ăn dặm cho bé | K30: merchant | L30: VND | M30: Giao hàng thành công | N30: ODVN260327733403EE | O30: 2603278B5XV70H | P30: 100 | Q30: 5x2x5 | R30: 1 | S30: 0 | T30: 0 | U30: 0 | V30: 0 | W30: 0 | X30: 0 | Y30: 0 | Z30: 0 | AA30: 8 | AB30: =Z30 -> 0 | AC30: =IF(AB30-S30<0,"YES","NO") -> NO | AD30: =IF(AC30="NO",0,AB30-S30) -> 0 | AE30: 0.08 | AF30: =AD30/(1+AE30) -> 0 | AG30: =AF30*1.1 -> 0
A31: 2026-03-27 12:01:29 | B31: 2026-03-27 12:09:22 | C31: 2026-03-27 14:07:37 | D31: 2026-03-27 14:17:30 | E31: 2026-03-27 14:47:40 | F31: 2026-03-28 10:33:34 | G31: shopee_v2 | H31: physical | I31: MON055GH04VAN | J31: Váng sữa Zott Monte vị Vani nhập khẩu từ ĐỨC, bé 6 tháng tuổi trở lên (vỉ - 55g x 4 hũ) từ Sữa tươi, KHÔNG chất bảo quản | K31: merchant | L31: VND | M31: Giao hàng thành công | N31: ODVN260327733403EE | O31: 2603278B5XV70H | P31: 220 | R31: 2 | S31: 150000 | T31: 160000 | U31: 0 | V31: 16000 | W31: 0 | X31: 28801 | Y31: 0 | Z31: 144000 | AA31: 8 | AB31: =Z31 -> 144000 | AC31: =IF(AB31-S31<0,"YES","NO") -> YES | AD31: =IF(AC31="NO",0,AB31-S31) -> -6000 | AE31: 0.08 | AF31: =AD31/(1+AE31) -> -5555.5556 | AG31: =AF31*1.1 -> -6111.1111
A32: 2026-03-27 11:57:22 | B32: 2026-03-27 12:04:17 | C32: 2026-03-27 13:55:17 | D32: 2026-03-27 14:32:33 | E32: 2026-03-27 15:33:46 | F32: 2026-03-30 16:52:17 | G32: shopee_v2 | H32: gift | I32: GIFT-YEMANDAM | J32: [HÀNG TẶNG KHÔNG BÁN] Yếm ăn dặm cho bé | K32: merchant | L32: VND | M32: Giao hàng thành công | N32: ODVN260327388966AD | O32: 2603278AXKBKVY | P32: 100 | Q32: 5x2x5 | R32: 1 | S32: 0 | T32: 0 | U32: 0 | V32: 0 | W32: 0 | X32: 0 | Y32: 0 | Z32: 0 | AA32: 8 | AB32: =Z32 -> 0 | AC32: =IF(AB32-S32<0,"YES","NO") -> NO | AD32: =IF(AC32="NO",0,AB32-S32) -> 0 | AE32: 0.08 | AF32: =AD32/(1+AE32) -> 0 | AG32: =AF32*1.1 -> 0
A33: 2026-03-27 11:57:22 | B33: 2026-03-27 12:04:17 | C33: 2026-03-27 13:55:17 | D33: 2026-03-27 14:32:33 | E33: 2026-03-27 15:33:46 | F33: 2026-03-30 16:52:17 | G33: shopee_v2 | H33: physical | I33: MON055GH04VAN | J33: Váng sữa Zott Monte vị Vani nhập khẩu từ ĐỨC, bé 6 tháng tuổi trở lên (vỉ - 55g x 4 hũ) từ Sữa tươi, KHÔNG chất bảo quản | K33: merchant | L33: VND | M33: Giao hàng thành công | N33: ODVN260327388966AD | O33: 2603278AXKBKVY | P33: 220 | R33: 6 | S33: 450000 | T33: 480000 | U33: 75000 | V33: 48000 | W33: 0 | X33: 132120 | Y33: 0 | Z33: 357000 | AA33: 8 | AB33: =Z33 -> 357000 | AC33: =IF(AB33-S33<0,"YES","NO") -> YES | AD33: =IF(AC33="NO",0,AB33-S33) -> -93000 | AE33: 0.08 | AF33: =AD33/(1+AE33) -> -86111.111 | AG33: =AF33*1.1 -> -94722.222
A34: 2026-03-27 11:37:20 | B34: 2026-03-27 11:52:35 | C34: 2026-03-27 13:43:18 | D34: 2026-03-27 14:07:38 | E34: 2026-03-27 15:00:14 | F34: 2026-03-28 09:49:57 | G34: shopee_v2 | H34: gift | I34: GIFT-BOBONGRO | J34: [HÀNG TẶNG KHÔNG BÁN] Bộ đồ chơi bóng rổ đáng yêu (hình ngẫu nhiên) | K34: merchant | L34: VND | M34: Giao hàng thành công | N34: ODVN260327780D5DBA | O34: 26032789TN70Y7 | P34: 20000 | Q34: 5x3x5 | R34: 1 | S34: 0 | T34: 0 | U34: 0 | V34: 0 | W34: 0 | X34: 0 | Y34: 0 | Z34: 0 | AA34: 8 | AB34: =Z34 -> 0 | AC34: =IF(AB34-S34<0,"YES","NO") -> NO | AD34: =IF(AC34="NO",0,AB34-S34) -> 0 | AE34: 0.08 | AF34: =AD34/(1+AE34) -> 0 | AG34: =AF34*1.1 -> 0
A35: 2026-03-27 11:37:20 | B35: 2026-03-27 11:52:35 | C35: 2026-03-27 13:43:18 | D35: 2026-03-27 14:07:38 | E35: 2026-03-27 15:00:14 | F35: 2026-03-28 09:49:57 | G35: shopee_v2 | H35: physical | I35: MNS055GC04MNG | J35: [Giao Hoả Tốc] Sữa chua Montinis vị Xoài nhập Đức (vỉ - 55g x 4 hũ) | K35: merchant | L35: VND | M35: Giao hàng thành công | N35: ODVN260327780D5DBA | O35: 26032789TN70Y7 | P35: 220 | Q35: 13x5x13 | R35: 1 | S35: 59000 | T35: 65000 | U35: 11666.67 | V35: 5000 | W35: 0 | X35: 21333.33 | Y35: 0 | Z35: 48333.33 | AA35: 8 | AB35: =Z35 -> 48333.33 | AC35: =IF(AB35-S35<0,"YES","NO") -> YES | AD35: =IF(AC35="NO",0,AB35-S35) -> -10666.67 | AE35: 0.08 | AF35: =AD35/(1+AE35) -> -9876.5463 | AG35: =AF35*1.1 -> -10864.201
A36: 2026-03-27 11:37:20 | B36: 2026-03-27 11:52:35 | C36: 2026-03-27 13:43:18 | D36: 2026-03-27 14:07:38 | E36: 2026-03-27 15:00:14 | F36: 2026-03-28 09:49:57 | G36: shopee_v2 | H36: physical | I36: MNS055GC04PLN | J36: [Giao Hoả Tốc] Sữa chua Montinis vị Nguyên bản nhập Đức (vỉ - 55g x 4 hũ) | K36: merchant | L36: VND | M36: Giao hàng thành công | N36: ODVN260327780D5DBA | O36: 26032789TN70Y7 | P36: 220 | Q36: 13x5x13 | R36: 1 | S36: 59000 | T36: 65000 | U36: 11666.67 | V36: 5000 | W36: 0 | X36: 21333.33 | Y36: 0 | Z36: 48333.33 | AA36: 8 | AB36: =Z36 -> 48333.33 | AC36: =IF(AB36-S36<0,"YES","NO") -> YES | AD36: =IF(AC36="NO",0,AB36-S36) -> -10666.67 | AE36: 0.08 | AF36: =AD36/(1+AE36) -> -9876.5463 | AG36: =AF36*1.1 -> -10864.201
A37: 2026-03-27 11:37:20 | B37: 2026-03-27 11:52:35 | C37: 2026-03-27 13:43:18 | D37: 2026-03-27 14:07:38 | E37: 2026-03-27 15:00:14 | F37: 2026-03-28 09:49:57 | G37: shopee_v2 | H37: physical | I37: MNS055GC04APL | J37: [Giao Hoả Tốc] Sữa chua Montinis vị Táo nhập Đức (vỉ - 55g x 4 hũ) | K37: merchant | L37: VND | M37: Giao hàng thành công | N37: ODVN260327780D5DBA | O37: 26032789TN70Y7 | P37: 220 | Q37: 13x5x13 | R37: 1 | S37: 59000 | T37: 65000 | U37: 11666.67 | V37: 5000 | W37: 0 | X37: 21333.33 | Y37: 0 | Z37: 48333.33 | AA37: 8 | AB37: =Z37 -> 48333.33 | AC37: =IF(AB37-S37<0,"YES","NO") -> YES | AD37: =IF(AC37="NO",0,AB37-S37) -> -10666.67 | AE37: 0.08 | AF37: =AD37/(1+AE37) -> -9876.5463 | AG37: =AF37*1.1 -> -10864.201
A38: 2026-03-27 11:35:24 | B38: 2026-03-27 11:52:43 | C38: 2026-03-27 13:40:43 | D38: 2026-03-27 14:23:24 | E38: 2026-03-27 15:08:25 | F38: 2026-03-28 09:36:06 | G38: shopee_v2 | H38: gift | I38: GIFT-YEMANDAM | J38: [HÀNG TẶNG KHÔNG BÁN] Yếm ăn dặm cho bé | K38: merchant | L38: VND | M38: Giao hàng thành công | N38: ODVN2603277A38A248 | O38: 26032789QAC0ET | P38: 100 | Q38: 5x2x5 | R38: 1 | S38: 0 | T38: 0 | U38: 0 | V38: 0 | W38: 0 | X38: 0 | Y38: 0 | Z38: 0 | AA38: 8 | AB38: =Z38 -> 0 | AC38: =IF(AB38-S38<0,"YES","NO") -> NO | AD38: =IF(AC38="NO",0,AB38-S38) -> 0 | AE38: 0.08 | AF38: =AD38/(1+AE38) -> 0 | AG38: =AF38*1.1 -> 0
A39: 2026-03-27 11:35:24 | B39: 2026-03-27 11:52:43 | C39: 2026-03-27 13:40:43 | D39: 2026-03-27 14:23:24 | E39: 2026-03-27 15:08:25 | F39: 2026-03-28 09:36:06 | G39: shopee_v2 | H39: physical | I39: MON055GH04VAN | J39: Váng sữa Zott Monte vị Vani nhập khẩu từ ĐỨC, bé 6 tháng tuổi trở lên (vỉ - 55g x 4 hũ) từ Sữa tươi, KHÔNG chất bảo quản | K39: merchant | L39: VND | M39: Giao hàng thành công | N39: ODVN2603277A38A248 | O39: 26032789QAC0ET | P39: 220 | R39: 2 | S39: 150000 | T39: 160000 | U39: 10628 | V39: 16000 | W39: 0 | X39: 37197 | Y39: 0 | Z39: 133372 | AA39: 8 | AB39: =Z39 -> 133372 | AC39: =IF(AB39-S39<0,"YES","NO") -> YES | AD39: =IF(AC39="NO",0,AB39-S39) -> -16628 | AE39: 0.08 | AF39: =AD39/(1+AE39) -> -15396.296 | AG39: =AF39*1.1 -> -16935.926
A40: 2026-03-27 11:35:24 | B40: 2026-03-27 11:52:43 | C40: 2026-03-27 13:40:43 | D40: 2026-03-27 14:23:24 | E40: 2026-03-27 15:08:25 | F40: 2026-03-28 09:36:06 | G40: shopee_v2 | H40: physical | I40: MNF055GC04STB | J40: [Giao Hỏa Tốc] Phô mai tươi Montinis vị Dâu nhập ĐỨC (vỉ - 55g x 4 hũ) | K40: merchant | L40: VND | M40: Giao hàng thành công | N40: ODVN2603277A38A248 | O40: 26032789QAC0ET | P40: 220 | Q40: 10x5x15 | R40: 1 | S40: 59000 | T40: 70000 | U40: 4686 | V40: 6500 | W40: 0 | X40: 16401.5 | Y40: 0 | Z40: 58814 | AA40: 8 | AB40: =Z40 -> 58814 | AC40: =IF(AB40-S40<0,"YES","NO") -> YES | AD40: =IF(AC40="NO",0,AB40-S40) -> -186 | AE40: 0.08 | AF40: =AD40/(1+AE40) -> -172.22222 | AG40: =AF40*1.1 -> -189.44444
A41: 2026-03-27 11:35:24 | B41: 2026-03-27 11:52:43 | C41: 2026-03-27 13:40:43 | D41: 2026-03-27 14:23:24 | E41: 2026-03-27 15:08:25 | F41: 2026-03-28 09:36:06 | G41: shopee_v2 | H41: physical | I41: MNF055GC04VAN | J41: [Giao Hỏa Tốc] Phô mai tươi Montinis vị Vani nhập ĐỨC (vỉ - 55g x 4 hũ) | K41: merchant | L41: VND | M41: Giao hàng thành công | N41: ODVN2603277A38A248 | O41: 26032789QAC0ET | P41: 220 | Q41: 10x10x15 | R41: 1 | S41: 59000 | T41: 70000 | U41: 4686 | V41: 6500 | W41: 0 | X41: 16401.5 | Y41: 0 | Z41: 58814 | AA41: 8 | AB41: =Z41 -> 58814 | AC41: =IF(AB41-S41<0,"YES","NO") -> YES | AD41: =IF(AC41="NO",0,AB41-S41) -> -186 | AE41: 0.08 | AF41: =AD41/(1+AE41) -> -172.22222 | AG41: =AF41*1.1 -> -189.44444
A42: 2026-03-27 09:59:06 | B42: 2026-03-27 10:51:00 | C42: 2026-03-27 16:35:01 | D42: 2026-03-27 17:29:17 | E42: 2026-03-27 18:07:29 | F42: 2026-03-30 19:41:49 | G42: shopee_v2 | H42: physical | I42: MNS055GC04MNG | J42: [Giao Hoả Tốc] Sữa chua Montinis vị Xoài nhập Đức (vỉ - 55g x 4 hũ) | K42: merchant | L42: VND | M42: Giao hàng thành công | N42: ODVN26032718B6E878 | O42: 26032784B41TE0 | P42: 220 | Q42: 13x5x13 | R42: 2 | S42: 118000 | T42: 130000 | U42: 11666.66 | V42: 10000 | W42: 0 | X42: 29000 | Y42: 0 | Z42: 108333.34 | AA42: 8 | AB42: =Z42 -> 108333.34 | AC42: =IF(AB42-S42<0,"YES","NO") -> YES | AD42: =IF(AC42="NO",0,AB42-S42) -> -9666.66 | AE42: 0.08 | AF42: =AD42/(1+AE42) -> -8950.6111 | AG42: =AF42*1.1 -> -9845.6722
A43: 2026-03-27 09:59:06 | B43: 2026-03-27 10:51:00 | C43: 2026-03-27 16:35:01 | D43: 2026-03-27 17:29:17 | E43: 2026-03-27 18:07:29 | F43: 2026-03-30 19:41:49 | G43: shopee_v2 | H43: physical | I43: MNS055GC04PLN | J43: [Giao Hoả Tốc] Sữa chua Montinis vị Nguyên bản nhập Đức (vỉ - 55g x 4 hũ) | K43: merchant | L43: VND | M43: Giao hàng thành công | N43: ODVN26032718B6E878 | O43: 26032784B41TE0 | P43: 220 | Q43: 13x5x13 | R43: 2 | S43: 118000 | T43: 130000 | U43: 11666.66 | V43: 10000 | W43: 0 | X43: 29000 | Y43: 0 | Z43: 108333.34 | AA43: 8 | AB43: =Z43 -> 108333.34 | AC43: =IF(AB43-S43<0,"YES","NO") -> YES | AD43: =IF(AC43="NO",0,AB43-S43) -> -9666.66 | AE43: 0.08 | AF43: =AD43/(1+AE43) -> -8950.6111 | AG43: =AF43*1.1 -> -9845.6722
A44: 2026-03-27 09:59:06 | B44: 2026-03-27 10:51:00 | C44: 2026-03-27 16:35:01 | D44: 2026-03-27 17:29:17 | E44: 2026-03-27 18:07:29 | F44: 2026-03-30 19:41:49 | G44: shopee_v2 | H44: physical | I44: MNS055GC04APL | J44: [Giao Hoả Tốc] Sữa chua Montinis vị Táo nhập Đức (vỉ - 55g x 4 hũ) | K44: merchant | L44: VND | M44: Giao hàng thành công | N44: ODVN26032718B6E878 | O44: 26032784B41TE0 | P44: 220 | Q44: 13x5x13 | R44: 2 | S44: 118000 | T44: 130000 | U44: 11666.66 | V44: 10000 | W44: 0 | X44: 29000 | Y44: 0 | Z44: 108333.34 | AA44: 8 | AB44: =Z44 -> 108333.34 | AC44: =IF(AB44-S44<0,"YES","NO") -> YES | AD44: =IF(AC44="NO",0,AB44-S44) -> -9666.66 | AE44: 0.08 | AF44: =AD44/(1+AE44) -> -8950.6111 | AG44: =AF44*1.1 -> -9845.6722
A45: 2026-03-27 09:57:34 | B45: 2026-03-27 10:51:10 | C45: 2026-03-27 13:38:25 | D45: 2026-03-27 14:06:35 | E45: 2026-03-27 15:07:01 | F45: 2026-03-28 09:51:37 | G45: shopee_v2 | H45: gift | I45: GIFT-TAPDEGMS | J45: [HÀNG TẶNG KHÔNG BÁN] Tạp dề vào bếp xinh xắn Zott Gourmet Slices (màu ngẫu nhiên) | K45: merchant | L45: VND | M45: Giao hàng thành công | N45: ODVN260327A4B9C658 | O45: 260327848CAWH3 | P45: 20 | Q45: 5x2x5 | R45: 1 | S45: 0 | T45: 0 | U45: 0 | V45: 0 | W45: 0 | X45: 0 | Y45: 0 | Z45: 0 | AA45: 8 | AB45: =Z45 -> 0 | AC45: =IF(AB45-S45<0,"YES","NO") -> NO | AD45: =IF(AC45="NO",0,AB45-S45) -> 0 | AE45: 0.08 | AF45: =AD45/(1+AE45) -> 0 | AG45: =AF45*1.1 -> 0
A46: 2026-03-27 09:57:34 | B46: 2026-03-27 10:51:10 | C46: 2026-03-27 13:38:25 | D46: 2026-03-27 14:06:35 | E46: 2026-03-27 15:07:01 | F46: 2026-03-28 09:51:37 | G46: shopee_v2 | H46: physical | I46: GMS200GL12BGR | J46: Phô mai lát Zott Gourmet Slices BURGER nhập khẩu từ Đức, phù hợp cả gia đình (1 gói 200g – 12 lát), làm từ Sữa tươi giàu Canxi, Chất đạm | K46: merchant | L46: VND | M46: Giao hàng thành công | N46: ODVN260327A4B9C658 | O46: 260327848CAWH3 | P46: 200 | R46: 3 | S46: 216000 | T46: 240000 | U46: 34999.98 | V46: 20000.01 | W46: 0 | X46: 68299.98 | Y46: 0 | Z46: 185000.01 | AA46: 8 | AB46: =Z46 -> 185000.01 | AC46: =IF(AB46-S46<0,"YES","NO") -> YES | AD46: =IF(AC46="NO",0,AB46-S46) -> -30999.99 | AE46: 0.08 | AF46: =AD46/(1+AE46) -> -28703.694 | AG46: =AF46*1.1 -> -31574.064
A47: 2026-03-27 09:53:15 | B47: 2026-03-27 09:55:12 | C47: 2026-03-27 10:52:48 | D47: 2026-03-27 12:06:10 | E47: 2026-03-27 12:11:25 | F47: 2026-03-28 09:44:50 | G47: shopee_v2 | H47: physical | I47: MNS055GC04MNG | J47: [Giao Hoả Tốc] Sữa chua Montinis vị Xoài nhập Đức (vỉ - 55g x 4 hũ) | K47: merchant | L47: VND | M47: Giao hàng thành công | N47: ODVN2603277BD181B5 | O47: 260327840MBKC7 | P47: 220 | Q47: 13x5x13 | R47: 1 | S47: 59000 | T47: 65000 | U47: 11666.67 | V47: 5000 | W47: 0 | X47: 21333.33 | Y47: 0 | Z47: 48333.33 | AA47: 8 | AB47: =Z47 -> 48333.33 | AC47: =IF(AB47-S47<0,"YES","NO") -> YES | AD47: =IF(AC47="NO",0,AB47-S47) -> -10666.67 | AE47: 0.08 | AF47: =AD47/(1+AE47) -> -9876.5463 | AG47: =AF47*1.1 -> -10864.201
A48: 2026-03-27 09:53:15 | B48: 2026-03-27 09:55:12 | C48: 2026-03-27 10:52:48 | D48: 2026-03-27 12:06:10 | E48: 2026-03-27 12:11:25 | F48: 2026-03-28 09:44:50 | G48: shopee_v2 | H48: physical | I48: MNS055GC04PLN | J48: [Giao Hoả Tốc] Sữa chua Montinis vị Nguyên bản nhập Đức (vỉ - 55g x 4 hũ) | K48: merchant | L48: VND | M48: Giao hàng thành công | N48: ODVN2603277BD181B5 | O48: 260327840MBKC7 | P48: 220 | Q48: 13x5x13 | R48: 1 | S48: 59000 | T48: 65000 | U48: 11666.67 | V48: 5000 | W48: 0 | X48: 21333.33 | Y48: 0 | Z48: 48333.33 | AA48: 8 | AB48: =Z48 -> 48333.33 | AC48: =IF(AB48-S48<0,"YES","NO") -> YES | AD48: =IF(AC48="NO",0,AB48-S48) -> -10666.67 | AE48: 0.08 | AF48: =AD48/(1+AE48) -> -9876.5463 | AG48: =AF48*1.1 -> -10864.201
A49: 2026-03-27 09:53:15 | B49: 2026-03-27 09:55:12 | C49: 2026-03-27 10:52:48 | D49: 2026-03-27 12:06:10 | E49: 2026-03-27 12:11:25 | F49: 2026-03-28 09:44:50 | G49: shopee_v2 | H49: physical | I49: MNS055GC04APL | J49: [Giao Hoả Tốc] Sữa chua Montinis vị Táo nhập Đức (vỉ - 55g x 4 hũ) | K49: merchant | L49: VND | M49: Giao hàng thành công | N49: ODVN2603277BD181B5 | O49: 260327840MBKC7 | P49: 220 | Q49: 13x5x13 | R49: 1 | S49: 59000 | T49: 65000 | U49: 11666.67 | V49: 5000 | W49: 0 | X49: 21333.33 | Y49: 0 | Z49: 48333.33 | AA49: 8 | AB49: =Z49 -> 48333.33 | AC49: =IF(AB49-S49<0,"YES","NO") -> YES | AD49: =IF(AC49="NO",0,AB49-S49) -> -10666.67 | AE49: 0.08 | AF49: =AD49/(1+AE49) -> -9876.5463 | AG49: =AF49*1.1 -> -10864.201
A50: 2026-03-27 07:22:32 | B50: 2026-03-27 07:23:43 | C50: 2026-03-27 07:52:42 | D50: 2026-03-27 08:38:45 | E50: 2026-03-27 09:30:48 | F50: 2026-03-30 10:12:52 | G50: shopee_v2 | H50: physical | I50: MON055GH04CXP | J50: [Giao nhanh 2H] Váng sữa Zott Monte Canxi Plus nhập khẩu từ ĐỨC, bé 6 tháng tuổi trở lên (vỉ - 55g x 4 hũ) từ Sữa tươi, KHÔNG chất bảo quản | K50: merchant | L50: VND | M50: Giao hàng thành công | N50: ODVN260327F2B73EE6 | O50: 2603277UK57YSC | P50: 220 | R50: 6 | S50: 450000 | T50: 480000 | U50: 75000 | V50: 25000.02 | W50: 0 | X50: 135799.98 | Y50: 0 | Z50: 379999.98 | AA50: 8 | AB50: =Z50 -> 379999.98 | AC50: =IF(AB50-S50<0,"YES","NO") -> YES | AD50: =IF(AC50="NO",0,AB50-S50) -> -70000.02 | AE50: 0.08 | AF50: =AD50/(1+AE50) -> -64814.833 | AG50: =AF50*1.1 -> -71296.317
A51: 2026-03-27 00:03:47 | B51: 2026-03-27 00:05:47 | C51: 2026-03-27 08:42:42 | D51: 2026-03-27 09:24:21 | E51: 2026-03-27 09:53:09 | F51: 2026-03-30 10:10:26 | G51: shopee_v2 | H51: physical | I51: MNS055GC04MNG | J51: [Giao Hoả Tốc] Sữa chua Montinis vị Xoài nhập Đức (vỉ - 55g x 4 hũ) | K51: merchant | L51: VND | M51: Giao hàng thành công | N51: ODVN2603276E945C4E | O51: 260327732KQYB7 | P51: 220 | Q51: 13x5x13 | R51: 1 | S51: 59000 | T51: 65000 | U51: 11666.67 | V51: 5000 | W51: 0 | X51: 21333.33 | Y51: 0 | Z51: 48333.33 | AA51: 8 | AB51: =Z51 -> 48333.33 | AC51: =IF(AB51-S51<0,"YES","NO") -> YES | AD51: =IF(AC51="NO",0,AB51-S51) -> -10666.67 | AE51: 0.08 | AF51: =AD51/(1+AE51) -> -9876.5463 | AG51: =AF51*1.1 -> -10864.201
A52: 2026-03-27 00:03:47 | B52: 2026-03-27 00:05:47 | C52: 2026-03-27 08:42:42 | D52: 2026-03-27 09:24:21 | E52: 2026-03-27 09:53:09 | F52: 2026-03-30 10:10:26 | G52: shopee_v2 | H52: physical | I52: MNS055GC04PLN | J52: [Giao Hoả Tốc] Sữa chua Montinis vị Nguyên bản nhập Đức (vỉ - 55g x 4 hũ) | K52: merchant | L52: VND | M52: Giao hàng thành công | N52: ODVN2603276E945C4E | O52: 260327732KQYB7 | P52: 220 | Q52: 13x5x13 | R52: 1 | S52: 59000 | T52: 65000 | U52: 11666.67 | V52: 5000 | W52: 0 | X52: 21333.33 | Y52: 0 | Z52: 48333.33 | AA52: 8 | AB52: =Z52 -> 48333.33 | AC52: =IF(AB52-S52<0,"YES","NO") -> YES | AD52: =IF(AC52="NO",0,AB52-S52) -> -10666.67 | AE52: 0.08 | AF52: =AD52/(1+AE52) -> -9876.5463 | AG52: =AF52*1.1 -> -10864.201
A53: 2026-03-27 00:03:47 | B53: 2026-03-27 00:05:47 | C53: 2026-03-27 08:42:42 | D53: 2026-03-27 09:24:21 | E53: 2026-03-27 09:53:09 | F53: 2026-03-30 10:10:26 | G53: shopee_v2 | H53: physical | I53: MNS055GC04APL | J53: [Giao Hoả Tốc] Sữa chua Montinis vị Táo nhập Đức (vỉ - 55g x 4 hũ) | K53: merchant | L53: VND | M53: Giao hàng thành công | N53: ODVN2603276E945C4E | O53: 260327732KQYB7 | P53: 220 | Q53: 13x5x13 | R53: 1 | S53: 59000 | T53: 65000 | U53: 11666.67 | V53: 5000 | W53: 0 | X53: 21333.33 | Y53: 0 | Z53: 48333.33 | AA53: 8 | AB53: =Z53 -> 48333.33 | AC53: =IF(AB53-S53<0,"YES","NO") -> YES | AD53: =IF(AC53="NO",0,AB53-S53) -> -10666.67 | AE53: 0.08 | AF53: =AD53/(1+AE53) -> -9876.5463 | AG53: =AF53*1.1 -> -10864.201
A54: 2026-03-26 23:39:57 | B54: 2026-03-26 23:41:05 | C54: 2026-03-27 09:25:38 | D54: 2026-03-27 09:53:07 | E54: 2026-03-27 11:21:58 | F54: 2026-03-30 12:50:06 | G54: shopee_v2 | H54: gift | I54: GIFT-TAPDEGMS | J54: [HÀNG TẶNG KHÔNG BÁN] Tạp dề vào bếp xinh xắn Zott Gourmet Slices (màu ngẫu nhiên) | K54: merchant | L54: VND | M54: Giao hàng thành công | N54: ODVN260326A1D3BEBA | O54: 26032771QV6N4D | P54: 20 | Q54: 5x2x5 | R54: 1 | S54: 0 | T54: 0 | U54: 0 | V54: 0 | W54: 0 | X54: 0 | Y54: 0 | Z54: 0 | AA54: 8 | AB54: =Z54 -> 0 | AC54: =IF(AB54-S54<0,"YES","NO") -> NO | AD54: =IF(AC54="NO",0,AB54-S54) -> 0 | AE54: 0.08 | AF54: =AD54/(1+AE54) -> 0 | AG54: =AF54*1.1 -> 0
A55: 2026-03-26 23:39:57 | B55: 2026-03-26 23:41:05 | C55: 2026-03-27 09:25:38 | D55: 2026-03-27 09:53:07 | E55: 2026-03-27 11:21:58 | F55: 2026-03-30 12:50:06 | G55: shopee_v2 | H55: physical | I55: GMS200GL12BGR | J55: Phô mai lát Zott Gourmet Slices BURGER nhập khẩu từ Đức, phù hợp cả gia đình (1 gói 200g – 12 lát), làm từ Sữa tươi giàu Canxi, Chất đạm | K55: merchant | L55: VND | M55: Giao hàng thành công | N55: ODVN260326A1D3BEBA | O55: 26032771QV6N4D | P55: 200 | R55: 6 | S55: 432000 | T55: 480000 | U55: 79999.98 | V55: 40000.02 | W55: 0 | X55: 137599.98 | Y55: 0 | Z55: 360000 | AA55: 8 | AB55: =Z55 -> 360000 | AC55: =IF(AB55-S55<0,"YES","NO") -> YES | AD55: =IF(AC55="NO",0,AB55-S55) -> -72000 | AE55: 0.08 | AF55: =AD55/(1+AE55) -> -66666.667 | AG55: =AF55*1.1 -> -73333.333
A56: 2026-03-26 22:48:14 | B56: 2026-03-26 23:00:09 | C56: 2026-03-27 08:42:30 | D56: 2026-03-27 09:08:08 | E56: 2026-03-27 09:50:48 | F56: 2026-03-30 10:12:50 | G56: shopee_v2 | H56: physical | I56: MON055GH04VAN | J56: Váng sữa Zott Monte vị Vani nhập khẩu từ ĐỨC, bé 6 tháng tuổi trở lên (vỉ - 55g x 4 hũ) từ Sữa tươi, KHÔNG chất bảo quản | K56: merchant | L56: VND | M56: Giao hàng thành công | N56: ODVN260326788D033A | O56: 2603266XUGS4M0 | P56: 220 | R56: 2 | S56: 150000 | T56: 160000 | U56: 20000 | V56: 16000 | W56: 0 | X56: 34880 | Y56: 0 | Z56: 124000 | AA56: 8 | AB56: =Z56 -> 124000 | AC56: =IF(AB56-S56<0,"YES","NO") -> YES | AD56: =IF(AC56="NO",0,AB56-S56) -> -26000 | AE56: 0.08 | AF56: =AD56/(1+AE56) -> -24074.074 | AG56: =AF56*1.1 -> -26481.481
A57: 2026-03-26 19:41:01 | B57: 2026-03-26 19:46:51 | C57: 2026-03-27 09:25:36 | D57: 2026-03-27 09:52:15 | E57: 2026-03-27 10:06:49 | F57: 2026-03-30 00:04:55 | G57: shopee_v2 | H57: physical | I57: MON055GH04VAN | J57: Váng sữa Zott Monte vị Vani nhập khẩu từ ĐỨC, bé 6 tháng tuổi trở lên (vỉ - 55g x 4 hũ) từ Sữa tươi, KHÔNG chất bảo quản | K57: merchant | L57: VND | M57: Giao hàng thành công | N57: ODVN26032653B84A4E | O57: 2603266MCR63F5 | P57: 220 | R57: 3 | S57: 225000 | T57: 240000 | U57: 35000.01 | V57: 12999.99 | W57: 0 | X57: 73400.01 | Y57: 0 | Z57: 192000 | AA57: 8 | AB57: =Z57 -> 192000 | AC57: =IF(AB57-S57<0,"YES","NO") -> YES | AD57: =IF(AC57="NO",0,AB57-S57) -> -33000 | AE57: 0.08 | AF57: =AD57/(1+AE57) -> -30555.556 | AG57: =AF57*1.1 -> -33611.111
A58: 2026-03-26 13:48:45 | B58: 2026-03-26 13:56:01 | C58: 2026-03-26 13:57:31 | D58: 2026-03-26 14:10:43 | E58: 2026-03-26 14:37:30 | F58: 2026-03-29 15:41:41 | G58: shopee_v2 | H58: gift | I58: GIFT-BOBONGRO | J58: [HÀNG TẶNG KHÔNG BÁN] Bộ đồ chơi bóng rổ đáng yêu (hình ngẫu nhiên) | K58: merchant | L58: VND | M58: Giao hàng thành công | N58: ODVN26032654D974E1 | O58: 26032660PU9TXE | P58: 20000 | Q58: 5x3x5 | R58: 1 | S58: 0 | T58: 0 | U58: 0 | V58: 0 | W58: 0 | X58: 0 | Y58: 0 | Z58: 0 | AA58: 8 | AB58: =Z58 -> 0 | AC58: =IF(AB58-S58<0,"YES","NO") -> NO | AD58: =IF(AC58="NO",0,AB58-S58) -> 0 | AE58: 0.08 | AF58: =AD58/(1+AE58) -> 0 | AG58: =AF58*1.1 -> 0
A59: 2026-03-26 13:48:45 | B59: 2026-03-26 13:56:01 | C59: 2026-03-26 13:57:31 | D59: 2026-03-26 14:10:43 | E59: 2026-03-26 14:37:30 | F59: 2026-03-29 15:41:41 | G59: shopee_v2 | H59: physical | I59: MNS055GC04MNG | J59: [Giao Hoả Tốc] Sữa chua Montinis vị Xoài nhập Đức (vỉ - 55g x 4 hũ) | K59: merchant | L59: VND | M59: Giao hàng thành công | N59: ODVN26032654D974E1 | O59: 26032660PU9TXE | P59: 220 | Q59: 13x5x13 | R59: 1 | S59: 59000 | T59: 65000 | U59: 11666.67 | V59: 5000 | W59: 0 | X59: 17466.67 | Y59: 0 | Z59: 48333.33 | AA59: 8 | AB59: =Z59 -> 48333.33 | AC59: =IF(AB59-S59<0,"YES","NO") -> YES | AD59: =IF(AC59="NO",0,AB59-S59) -> -10666.67 | AE59: 0.08 | AF59: =AD59/(1+AE59) -> -9876.5463 | AG59: =AF59*1.1 -> -10864.201
A60: 2026-03-26 13:48:45 | B60: 2026-03-26 13:56:01 | C60: 2026-03-26 13:57:31 | D60: 2026-03-26 14:10:43 | E60: 2026-03-26 14:37:30 | F60: 2026-03-29 15:41:41 | G60: shopee_v2 | H60: physical | I60: MNS055GC04PLN | J60: [Giao Hoả Tốc] Sữa chua Montinis vị Nguyên bản nhập Đức (vỉ - 55g x 4 hũ) | K60: merchant | L60: VND | M60: Giao hàng thành công | N60: ODVN26032654D974E1 | O60: 26032660PU9TXE | P60: 220 | Q60: 13x5x13 | R60: 1 | S60: 59000 | T60: 65000 | U60: 11666.67 | V60: 5000 | W60: 0 | X60: 17466.67 | Y60: 0 | Z60: 48333.33 | AA60: 8 | AB60: =Z60 -> 48333.33 | AC60: =IF(AB60-S60<0,"YES","NO") -> YES | AD60: =IF(AC60="NO",0,AB60-S60) -> -10666.67 | AE60: 0.08 | AF60: =AD60/(1+AE60) -> -9876.5463 | AG60: =AF60*1.1 -> -10864.201
A61: 2026-03-26 13:48:45 | B61: 2026-03-26 13:56:01 | C61: 2026-03-26 13:57:31 | D61: 2026-03-26 14:10:43 | E61: 2026-03-26 14:37:30 | F61: 2026-03-29 15:41:41 | G61: shopee_v2 | H61: physical | I61: MNS055GC04APL | J61: [Giao Hoả Tốc] Sữa chua Montinis vị Táo nhập Đức (vỉ - 55g x 4 hũ) | K61: merchant | L61: VND | M61: Giao hàng thành công | N61: ODVN26032654D974E1 | O61: 26032660PU9TXE | P61: 220 | Q61: 13x5x13 | R61: 1 | S61: 59000 | T61: 65000 | U61: 11666.67 | V61: 5000 | W61: 0 | X61: 17466.67 | Y61: 0 | Z61: 48333.33 | AA61: 8 | AB61: =Z61 -> 48333.33 | AC61: =IF(AB61-S61<0,"YES","NO") -> YES | AD61: =IF(AC61="NO",0,AB61-S61) -> -10666.67 | AE61: 0.08 | AF61: =AD61/(1+AE61) -> -9876.5463 | AG61: =AF61*1.1 -> -10864.201
A62: 2026-03-26 13:33:30 | B62: 2026-03-26 13:34:41 | C62: 2026-03-26 13:39:34 | D62: 2026-03-26 13:59:34 | E62: 2026-03-26 14:05:03 | F62: 2026-03-27 12:47:16 | G62: shopee_v2 | H62: gift | I62: GIFT-TAPDEGMS | J62: [HÀNG TẶNG KHÔNG BÁN] Tạp dề vào bếp xinh xắn Zott Gourmet Slices (màu ngẫu nhiên) | K62: merchant | L62: VND | M62: Giao hàng thành công | N62: ODVN260326D52289BC | O62: 2603265YUEUK3X | P62: 20 | Q62: 5x2x5 | R62: 1 | S62: 0 | T62: 0 | U62: 0 | V62: 0 | W62: 0 | X62: 0 | Y62: 0 | Z62: 0 | AA62: 8 | AB62: =Z62 -> 0 | AC62: =IF(AB62-S62<0,"YES","NO") -> NO | AD62: =IF(AC62="NO",0,AB62-S62) -> 0 | AE62: 0.08 | AF62: =AD62/(1+AE62) -> 0 | AG62: =AF62*1.1 -> 0
A63: 2026-03-26 13:33:30 | B63: 2026-03-26 13:34:41 | C63: 2026-03-26 13:39:34 | D63: 2026-03-26 13:59:34 | E63: 2026-03-26 14:05:03 | F63: 2026-03-27 12:47:16 | G63: shopee_v2 | H63: physical | I63: GMS200GL12SDW | J63: Phô mai lát Zott Gourmet Slices SANDWICH nhập khẩu từ Đức, phù hợp cả gia đình (1 gói 200g – 12 lát), làm từ Sữa tươi giàu Canxi, Chất đạm | K63: merchant | L63: VND | M63: Giao hàng thành công | N63: ODVN260326D52289BC | O63: 2603265YUEUK3X | P63: 200 | R63: 6 | S63: 432000 | T63: 480000 | U63: 75000 | V63: 48000 | W63: 0 | X63: 128550 | Y63: 0 | Z63: 357000 | AA63: 8 | AB63: =Z63 -> 357000 | AC63: =IF(AB63-S63<0,"YES","NO") -> YES | AD63: =IF(AC63="NO",0,AB63-S63) -> -75000 | AE63: 0.08 | AF63: =AD63/(1+AE63) -> -69444.444 | AG63: =AF63*1.1 -> -76388.889
A64: 2026-03-26 13:14:44 | B64: 2026-03-26 13:15:51 | C64: 2026-03-26 13:45:39 | D64: 2026-03-26 14:11:16 | E64: 2026-03-26 15:09:24 | F64: 2026-03-28 16:47:29 | G64: shopee_v2 | H64: gift | I64: GIFT-TAPDEGMS | J64: [HÀNG TẶNG KHÔNG BÁN] Tạp dề vào bếp xinh xắn Zott Gourmet Slices (màu ngẫu nhiên) | K64: merchant | L64: VND | M64: Giao hàng thành công | N64: ODVN2603260454D191 | O64: 2603265XT0U3RP | P64: 20 | Q64: 5x2x5 | R64: 1 | S64: 0 | T64: 0 | U64: 0 | V64: 0 | W64: 0 | X64: 0 | Y64: 0 | Z64: 0 | AA64: 8 | AB64: =Z64 -> 0 | AC64: =IF(AB64-S64<0,"YES","NO") -> NO | AD64: =IF(AC64="NO",0,AB64-S64) -> 0 | AE64: 0.08 | AF64: =AD64/(1+AE64) -> 0 | AG64: =AF64*1.1 -> 0
A65: 2026-03-26 13:14:44 | B65: 2026-03-26 13:15:51 | C65: 2026-03-26 13:45:39 | D65: 2026-03-26 14:11:16 | E65: 2026-03-26 15:09:24 | F65: 2026-03-28 16:47:29 | G65: shopee_v2 | H65: physical | I65: GMS200GL12SDW | J65: Phô mai lát Zott Gourmet Slices SANDWICH nhập khẩu từ Đức, phù hợp cả gia đình (1 gói 200g – 12 lát), làm từ Sữa tươi giàu Canxi, Chất đạm | K65: merchant | L65: VND | M65: Giao hàng thành công | N65: ODVN2603260454D191 | O65: 2603265XT0U3RP | P65: 200 | R65: 12 | S65: 864000 | T65: 960000 | U65: 75000 | V65: 96000 | W65: 0 | X65: 201240 | Y65: 0 | Z65: 789000 | AA65: 8 | AB65: =Z65 -> 789000 | AC65: =IF(AB65-S65<0,"YES","NO") -> YES | AD65: =IF(AC65="NO",0,AB65-S65) -> -75000 | AE65: 0.08 | AF65: =AD65/(1+AE65) -> -69444.444 | AG65: =AF65*1.1 -> -76388.889
A66: 2026-03-26 12:48:33 | B66: 2026-03-26 12:53:56 | C66: 2026-03-26 13:51:14 | D66: 2026-03-26 14:01:46 | E66: 2026-03-26 14:14:47 | F66: 2026-03-26 16:02:06 | G66: shopee_v2 | H66: physical | I66: MON055GH04VAN | J66: Váng sữa Zott Monte vị Vani nhập khẩu từ ĐỨC, bé 6 tháng tuổi trở lên (vỉ - 55g x 4 hũ) từ Sữa tươi, KHÔNG chất bảo quản | K66: merchant | L66: VND | M66: Giao hàng thành công | N66: ODVN2603262AB23767 | O66: 2603265WB5NRG1 | P66: 220 | R66: 3 | S66: 225000 | T66: 240000 | U66: 35000.01 | V66: 24000 | W66: 0 | X66: 71199.99 | Y66: 0 | Z66: 180999.99 | AA66: 8 | AB66: =Z66 -> 180999.99 | AC66: =IF(AB66-S66<0,"YES","NO") -> YES | AD66: =IF(AC66="NO",0,AB66-S66) -> -44000.01 | AE66: 0.08 | AF66: =AD66/(1+AE66) -> -40740.75 | AG66: =AF66*1.1 -> -44814.825
A67: 2026-03-26 12:23:21 | B67: 2026-03-26 12:28:36 | C67: 2026-03-26 13:30:26 | D67: 2026-03-26 13:52:15 | E67: 2026-03-26 14:12:33 | F67: 2026-03-29 14:44:19 | G67: shopee_v2 | H67: gift | I67: GIFT-YEMANDAM | J67: [HÀNG TẶNG KHÔNG BÁN] Yếm ăn dặm cho bé | K67: merchant | L67: VND | M67: Giao hàng thành công | N67: ODVN260326AD3DA97A | O67: 2603265UX4NP2B | P67: 100 | Q67: 5x2x5 | R67: 1 | S67: 0 | T67: 0 | U67: 0 | V67: 0 | W67: 0 | X67: 0 | Y67: 0 | Z67: 0 | AA67: 8 | AB67: =Z67 -> 0 | AC67: =IF(AB67-S67<0,"YES","NO") -> NO | AD67: =IF(AC67="NO",0,AB67-S67) -> 0 | AE67: 0.08 | AF67: =AD67/(1+AE67) -> 0 | AG67: =AF67*1.1 -> 0
A68: 2026-03-26 12:23:21 | B68: 2026-03-26 12:28:36 | C68: 2026-03-26 13:30:26 | D68: 2026-03-26 13:52:15 | E68: 2026-03-26 14:12:33 | F68: 2026-03-29 14:44:19 | G68: shopee_v2 | H68: physical | I68: MON055GH04VAN | J68: Váng sữa Zott Monte vị Vani nhập khẩu từ ĐỨC, bé 6 tháng tuổi trở lên (vỉ - 55g x 4 hũ) từ Sữa tươi, KHÔNG chất bảo quản | K68: merchant | L68: VND | M68: Giao hàng thành công | N68: ODVN260326AD3DA97A | O68: 2603265UX4NP2B | P68: 220 | R68: 6 | S68: 450000 | T68: 480000 | U68: 75000 | V68: 48000 | W68: 0 | X68: 132120 | Y68: 0 | Z68: 357000 | AA68: 8 | AB68: =Z68 -> 357000 | AC68: =IF(AB68-S68<0,"YES","NO") -> YES | AD68: =IF(AC68="NO",0,AB68-S68) -> -93000 | AE68: 0.08 | AF68: =AD68/(1+AE68) -> -86111.111 | AG68: =AF68*1.1 -> -94722.222
A69: 2026-03-26 12:02:53 | B69: 2026-03-26 12:04:09 | C69: 2026-03-26 15:35:21 | D69: 2026-03-26 16:19:09 | E69: 2026-03-26 17:21:29 | F69: 2026-03-29 18:12:52 | G69: shopee_v2 | H69: gift | I69: GIFT-TAPDEGMS | J69: [HÀNG TẶNG KHÔNG BÁN] Tạp dề vào bếp xinh xắn Zott Gourmet Slices (màu ngẫu nhiên) | K69: merchant | L69: VND | M69: Giao hàng thành công | N69: ODVN26032600AD34A2 | O69: 2603265TSHGT9V | P69: 20 | Q69: 5x2x5 | R69: 1 | S69: 0 | T69: 0 | U69: 0 | V69: 0 | W69: 0 | X69: 0 | Y69: 0 | Z69: 0 | AA69: 8 | AB69: =Z69 -> 0 | AC69: =IF(AB69-S69<0,"YES","NO") -> NO | AD69: =IF(AC69="NO",0,AB69-S69) -> 0 | AE69: 0.08 | AF69: =AD69/(1+AE69) -> 0 | AG69: =AF69*1.1 -> 0
A70: 2026-03-26 12:02:53 | B70: 2026-03-26 12:04:09 | C70: 2026-03-26 15:35:21 | D70: 2026-03-26 16:19:09 | E70: 2026-03-26 17:21:29 | F70: 2026-03-29 18:12:52 | G70: shopee_v2 | H70: physical | I70: GMS200GL12MZR | J70: Phô mai lát Zott Gourmet Slices MOZZARELLA nhập khẩu từ Đức, phù hợp cả gia đình (1 gói 200g – 12 lát), làm từ Sữa tươi giàu Canxi, Chất đạm | K70: merchant | L70: VND | M70: Giao hàng thành công | N70: ODVN26032600AD34A2 | O70: 2603265TSHGT9V | P70: 200 | R70: 6 | S70: 432000 | T70: 480000 | U70: 75000 | V70: 48000 | W70: 0 | X70: 146400 | Y70: 0 | Z70: 357000 | AA70: 8 | AB70: =Z70 -> 357000 | AC70: =IF(AB70-S70<0,"YES","NO") -> YES | AD70: =IF(AC70="NO",0,AB70-S70) -> -75000 | AE70: 0.08 | AF70: =AD70/(1+AE70) -> -69444.444 | AG70: =AF70*1.1 -> -76388.889
A71: 2026-03-26 11:53:08 | B71: 2026-03-26 11:58:27 | C71: 2026-03-26 13:08:27 | D71: 2026-03-26 14:02:55 | E71: 2026-03-26 14:16:17 | F71: 2026-03-29 15:18:59 | G71: shopee_v2 | H71: physical | I71: MON055GH04VAN | J71: Váng sữa Zott Monte vị Vani nhập khẩu từ ĐỨC, bé 6 tháng tuổi trở lên (vỉ - 55g x 4 hũ) từ Sữa tươi, KHÔNG chất bảo quản | K71: merchant | L71: VND | M71: Giao hàng thành công | N71: ODVN26032643AA661B | O71: 2603265T7YTXG2 | P71: 220 | R71: 6 | S71: 450000 | T71: 480000 | U71: 75000 | V71: 49000.02 | W71: 0 | X71: 131959.98 | Y71: 0 | Z71: 355999.98 | AA71: 8 | AB71: =Z71 -> 355999.98 | AC71: =IF(AB71-S71<0,"YES","NO") -> YES | AD71: =IF(AC71="NO",0,AB71-S71) -> -94000.02 | AE71: 0.08 | AF71: =AD71/(1+AE71) -> -87037.056 | AG71: =AF71*1.1 -> -95740.761
A72: 2026-03-26 11:38:53 | B72: 2026-03-26 11:41:49 | C72: 2026-03-26 11:42:22 | D72: 2026-03-26 12:28:00 | E72: 2026-03-27 00:07:23 | F72: 2026-03-27 08:00:50 | G72: shopee_v2 | H72: gift | I72: GIFT-YEMANDAM | J72: [HÀNG TẶNG KHÔNG BÁN] Yếm ăn dặm cho bé | K72: merchant | L72: VND | M72: Giao hàng thành công | N72: ODVN2603268FF11CF8 | O72: 2603265SEM71A0 | P72: 100 | Q72: 5x2x5 | R72: 1 | S72: 0 | T72: 0 | U72: 0 | V72: 0 | W72: 0 | X72: 0 | Y72: 0 | Z72: 0 | AA72: 8 | AB72: =Z72 -> 0 | AC72: =IF(AB72-S72<0,"YES","NO") -> NO | AD72: =IF(AC72="NO",0,AB72-S72) -> 0 | AE72: 0.08 | AF72: =AD72/(1+AE72) -> 0 | AG72: =AF72*1.1 -> 0
A73: 2026-03-26 11:38:53 | B73: 2026-03-26 11:41:49 | C73: 2026-03-26 11:42:22 | D73: 2026-03-26 12:28:00 | E73: 2026-03-27 00:07:23 | F73: 2026-03-27 08:00:50 | G73: shopee_v2 | H73: physical | I73: MON055GH04VAN | J73: Váng sữa Zott Monte vị Vani nhập khẩu từ ĐỨC, bé 6 tháng tuổi trở lên (vỉ - 55g x 4 hũ) từ Sữa tươi, KHÔNG chất bảo quản | K73: merchant | L73: VND | M73: Giao hàng thành công | N73: ODVN2603268FF11CF8 | O73: 2603265SEM71A0 | P73: 220 | R73: 6 | S73: 450000 | T73: 480000 | U73: 0 | V73: 25000.02 | W73: 0 | X73: 81900 | Y73: 0 | Z73: 454999.98 | AA73: 8 | AB73: =Z73 -> 454999.98 | AC73: =IF(AB73-S73<0,"YES","NO") -> NO | AD73: =IF(AC73="NO",0,AB73-S73) -> 0 | AE73: 0.08 | AF73: =AD73/(1+AE73) -> 0 | AG73: =AF73*1.1 -> 0
A74: 2026-03-26 11:38:19 | B74: 2026-03-26 11:41:55 | C74: 2026-03-26 13:30:24 | D74: 2026-03-26 13:51:58 | E74: 2026-03-26 14:33:23 | F74: 2026-03-27 08:02:04 | G74: shopee_v2 | H74: gift | I74: GIFT-YEMANDAM | J74: [HÀNG TẶNG KHÔNG BÁN] Yếm ăn dặm cho bé | K74: merchant | L74: VND | M74: Giao hàng thành công | N74: ODVN260326ADE6EF6B | O74: 2603265SDKT4KM | P74: 100 | Q74: 5x2x5 | R74: 1 | S74: 0 | T74: 0 | U74: 0 | V74: 0 | W74: 0 | X74: 0 | Y74: 0 | Z74: 0 | AA74: 8 | AB74: =Z74 -> 0 | AC74: =IF(AB74-S74<0,"YES","NO") -> NO | AD74: =IF(AC74="NO",0,AB74-S74) -> 0 | AE74: 0.08 | AF74: =AD74/(1+AE74) -> 0 | AG74: =AF74*1.1 -> 0
A75: 2026-03-26 11:38:19 | B75: 2026-03-26 11:41:55 | C75: 2026-03-26 13:30:24 | D75: 2026-03-26 13:51:58 | E75: 2026-03-26 14:33:23 | F75: 2026-03-27 08:02:04 | G75: shopee_v2 | H75: physical | I75: MON055GH04VAN | J75: Váng sữa Zott Monte vị Vani nhập khẩu từ ĐỨC, bé 6 tháng tuổi trở lên (vỉ - 55g x 4 hũ) từ Sữa tươi, KHÔNG chất bảo quản | K75: merchant | L75: VND | M75: Giao hàng thành công | N75: ODVN260326ADE6EF6B | O75: 2603265SDKT4KM | P75: 220 | R75: 3 | S75: 225000 | T75: 240000 | U75: 35000.01 | V75: 24000 | W75: 0 | X75: 71199.99 | Y75: 0 | Z75: 180999.99 | AA75: 8 | AB75: =Z75 -> 180999.99 | AC75: =IF(AB75-S75<0,"YES","NO") -> YES | AD75: =IF(AC75="NO",0,AB75-S75) -> -44000.01 | AE75: 0.08 | AF75: =AD75/(1+AE75) -> -40740.75 | AG75: =AF75*1.1 -> -44814.825
A76: 2026-03-26 10:52:31 | B76: 2026-03-26 10:57:47 | C76: 2026-03-26 11:02:42 | D76: 2026-03-26 11:25:03 | E76: 2026-03-26 11:50:47 | F76: 2026-03-29 12:40:24 | G76: shopee_v2 | H76: gift | I76: GIFT-YEMANDAM | J76: [HÀNG TẶNG KHÔNG BÁN] Yếm ăn dặm cho bé | K76: merchant | L76: VND | M76: Giao hàng thành công | N76: ODVN260326B491D92C | O76: 2603265PUQ51NH | P76: 100 | Q76: 5x2x5 | R76: 1 | S76: 0 | T76: 0 | U76: 0 | V76: 0 | W76: 0 | X76: 0 | Y76: 0 | Z76: 0 | AA76: 8 | AB76: =Z76 -> 0 | AC76: =IF(AB76-S76<0,"YES","NO") -> NO | AD76: =IF(AC76="NO",0,AB76-S76) -> 0 | AE76: 0.08 | AF76: =AD76/(1+AE76) -> 0 | AG76: =AF76*1.1 -> 0
A77: 2026-03-26 10:52:31 | B77: 2026-03-26 10:57:47 | C77: 2026-03-26 11:02:42 | D77: 2026-03-26 11:25:03 | E77: 2026-03-26 11:50:47 | F77: 2026-03-29 12:40:24 | G77: shopee_v2 | H77: physical | I77: MON055GH04VAN | J77: Váng sữa Zott Monte vị Vani nhập khẩu từ ĐỨC, bé 6 tháng tuổi trở lên (vỉ - 55g x 4 hũ) từ Sữa tươi, KHÔNG chất bảo quản | K77: merchant | L77: VND | M77: Giao hàng thành công | N77: ODVN260326B491D92C | O77: 2603265PUQ51NH | P77: 220 | R77: 2 | S77: 150000 | T77: 160000 | U77: 20000 | V77: 16000 | W77: 0 | X77: 44800 | Y77: 0 | Z77: 124000 | AA77: 8 | AB77: =Z77 -> 124000 | AC77: =IF(AB77-S77<0,"YES","NO") -> YES | AD77: =IF(AC77="NO",0,AB77-S77) -> -26000 | AE77: 0.08 | AF77: =AD77/(1+AE77) -> -24074.074 | AG77: =AF77*1.1 -> -26481.481
A78: 2026-03-25 23:24:50 | B78: 2026-03-25 23:30:04 | C78: 2026-03-26 08:34:21 | D78: 2026-03-26 08:56:44 | E78: 2026-03-26 09:26:24 | F78: 2026-03-27 19:15:38 | G78: shopee_v2 | H78: physical | I78: MNS055GC04MNG | J78: [Giao Hoả Tốc] Sữa chua Montinis vị Xoài nhập Đức (vỉ - 55g x 4 hũ) | K78: merchant | L78: VND | M78: Giao hàng thành công | N78: ODVN2603254B7105C4 | O78: 2603264GDCMQAU | P78: 220 | Q78: 13x5x13 | R78: 1 | S78: 59000 | T78: 65000 | U78: 11666.67 | V78: 6500 | W78: 0 | X78: 21033.33 | Y78: 0 | Z78: 46833.33 | AA78: 8 | AB78: =Z78 -> 46833.33 | AC78: =IF(AB78-S78<0,"YES","NO") -> YES | AD78: =IF(AC78="NO",0,AB78-S78) -> -12166.67 | AE78: 0.08 | AF78: =AD78/(1+AE78) -> -11265.435 | AG78: =AF78*1.1 -> -12391.979
A79: 2026-03-25 23:24:50 | B79: 2026-03-25 23:30:04 | C79: 2026-03-26 08:34:21 | D79: 2026-03-26 08:56:44 | E79: 2026-03-26 09:26:24 | F79: 2026-03-27 19:15:38 | G79: shopee_v2 | H79: physical | I79: MNS055GC04PLN | J79: [Giao Hoả Tốc] Sữa chua Montinis vị Nguyên bản nhập Đức (vỉ - 55g x 4 hũ) | K79: merchant | L79: VND | M79: Giao hàng thành công | N79: ODVN2603254B7105C4 | O79: 2603264GDCMQAU | P79: 220 | Q79: 13x5x13 | R79: 1 | S79: 59000 | T79: 65000 | U79: 11666.67 | V79: 6500 | W79: 0 | X79: 21033.33 | Y79: 0 | Z79: 46833.33 | AA79: 8 | AB79: =Z79 -> 46833.33 | AC79: =IF(AB79-S79<0,"YES","NO") -> YES | AD79: =IF(AC79="NO",0,AB79-S79) -> -12166.67 | AE79: 0.08 | AF79: =AD79/(1+AE79) -> -11265.435 | AG79: =AF79*1.1 -> -12391.979
A80: 2026-03-25 23:24:50 | B80: 2026-03-25 23:30:04 | C80: 2026-03-26 08:34:21 | D80: 2026-03-26 08:56:44 | E80: 2026-03-26 09:26:24 | F80: 2026-03-27 19:15:38 | G80: shopee_v2 | H80: physical | I80: MNS055GC04APL | J80: [Giao Hoả Tốc] Sữa chua Montinis vị Táo nhập Đức (vỉ - 55g x 4 hũ) | K80: merchant | L80: VND | M80: Giao hàng thành công | N80: ODVN2603254B7105C4 | O80: 2603264GDCMQAU | P80: 220 | Q80: 13x5x13 | R80: 1 | S80: 59000 | T80: 65000 | U80: 11666.67 | V80: 6500 | W80: 0 | X80: 21033.33 | Y80: 0 | Z80: 46833.33 | AA80: 8 | AB80: =Z80 -> 46833.33 | AC80: =IF(AB80-S80<0,"YES","NO") -> YES | AD80: =IF(AC80="NO",0,AB80-S80) -> -12166.67 | AE80: 0.08 | AF80: =AD80/(1+AE80) -> -11265.435 | AG80: =AF80*1.1 -> -12391.979
A81: 2026-03-25 23:12:00 | B81: 2026-03-25 23:17:15 | C81: 2026-03-26 08:34:34 | D81: 2026-03-26 09:09:53 | E81: 2026-03-26 10:56:30 | F81: 2026-03-26 12:28:32 | G81: shopee_v2 | H81: physical | I81: MNS055GC04MNG | J81: [Giao Hoả Tốc] Sữa chua Montinis vị Xoài nhập Đức (vỉ - 55g x 4 hũ) | K81: merchant | L81: VND | M81: Giao hàng thành công | N81: ODVN260325A1BD300D | O81: 2603264FQ29SD9 | P81: 220 | Q81: 13x5x13 | R81: 2 | S81: 118000 | T81: 130000 | U81: 0 | V81: 13000 | W81: 0 | X81: 23400 | Y81: 0 | Z81: 117000 | AA81: 8 | AB81: =Z81 -> 117000 | AC81: =IF(AB81-S81<0,"YES","NO") -> YES | AD81: =IF(AC81="NO",0,AB81-S81) -> -1000 | AE81: 0.08 | AF81: =AD81/(1+AE81) -> -925.92593 | AG81: =AF81*1.1 -> -1018.5185
A82: 2026-03-25 23:12:00 | B82: 2026-03-25 23:17:15 | C82: 2026-03-26 08:34:34 | D82: 2026-03-26 09:09:53 | E82: 2026-03-26 10:56:30 | F82: 2026-03-26 12:28:32 | G82: shopee_v2 | H82: physical | I82: MNS055GC04PLN | J82: [Giao Hoả Tốc] Sữa chua Montinis vị Nguyên bản nhập Đức (vỉ - 55g x 4 hũ) | K82: merchant | L82: VND | M82: Giao hàng thành công | N82: ODVN260325A1BD300D | O82: 2603264FQ29SD9 | P82: 220 | Q82: 13x5x13 | R82: 3 | S82: 177000 | T82: 195000 | U82: 35000.01 | V82: 19500 | W82: 0 | X82: 63099.99 | Y82: 0 | Z82: 140499.99 | AA82: 8 | AB82: =Z82 -> 140499.99 | AC82: =IF(AB82-S82<0,"YES","NO") -> YES | AD82: =IF(AC82="NO",0,AB82-S82) -> -36500.01 | AE82: 0.08 | AF82: =AD82/(1+AE82) -> -33796.306 | AG82: =AF82*1.1 -> -37175.936
A83: 2026-03-25 22:58:20 | B83: 2026-03-25 23:03:36 | C83: 2026-03-26 08:40:24 | D83: 2026-03-26 10:10:05 | E83: 2026-03-26 11:08:25 | F83: 2026-03-27 00:43:23 | G83: shopee_v2 | H83: physical | I83: MNS055GC04PLN | J83: [Giao Hoả Tốc] Sữa chua Montinis vị Nguyên bản nhập Đức (vỉ - 55g x 4 hũ) | K83: merchant | L83: VND | M83: Giao hàng thành công | N83: ODVN260325D75F3EC4 | O83: 2603254EXN7EM7 | P83: 220 | Q83: 13x5x13 | R83: 3 | S83: 177000 | T83: 195000 | U83: 15689.01 | V83: 19500 | W83: 0 | X83: 47651.01 | Y83: 0 | Z83: 159810.99 | AA83: 8 | AB83: =Z83 -> 159810.99 | AC83: =IF(AB83-S83<0,"YES","NO") -> YES | AD83: =IF(AC83="NO",0,AB83-S83) -> -17189.01 | AE83: 0.08 | AF83: =AD83/(1+AE83) -> -15915.75 | AG83: =AF83*1.1 -> -17507.325
A84: 2026-03-25 22:58:20 | B84: 2026-03-25 23:03:36 | C84: 2026-03-26 08:40:24 | D84: 2026-03-26 10:10:05 | E84: 2026-03-26 11:08:25 | F84: 2026-03-27 00:43:23 | G84: shopee_v2 | H84: physical | I84: MON055GH04CXP | J84: [Giao nhanh 2H] Váng sữa Zott Monte Canxi Plus nhập khẩu từ ĐỨC, bé 6 tháng tuổi trở lên (vỉ - 55g x 4 hũ) từ Sữa tươi, KHÔNG chất bảo quản | K84: merchant | L84: VND | M84: Giao hàng thành công | N84: ODVN260325D75F3EC4 | O84: 2603254EXN7EM7 | P84: 220 | R84: 3 | S84: 225000 | T84: 240000 | U84: 19311 | V84: 24000 | W84: 0 | X84: 58649.01 | Y84: 0 | Z84: 196689 | AA84: 8 | AB84: =Z84 -> 196689 | AC84: =IF(AB84-S84<0,"YES","NO") -> YES | AD84: =IF(AC84="NO",0,AB84-S84) -> -28311 | AE84: 0.08 | AF84: =AD84/(1+AE84) -> -26213.889 | AG84: =AF84*1.1 -> -28835.278
A85: 2026-03-25 20:27:33 | B85: 2026-03-25 20:28:54 | C85: 2026-03-26 08:40:18 | D85: 2026-03-26 09:40:12 | E85: 2026-03-26 10:50:10 | F85: 2026-03-26 13:44:58 | G85: shopee_v2 | H85: physical | I85: MON055GH04VAN | J85: Váng sữa Zott Monte vị Vani nhập khẩu từ ĐỨC, bé 6 tháng tuổi trở lên (vỉ - 55g x 4 hũ) từ Sữa tươi, KHÔNG chất bảo quản | K85: merchant | L85: VND | M85: Giao hàng thành công | N85: ODVN260325E5B1E91B | O85: 26032546H1A901 | P85: 220 | R85: 6 | S85: 450000 | T85: 480000 | U85: 75000 | V85: 48000 | W85: 0 | X85: 146400 | Y85: 0 | Z85: 357000 | AA85: 8 | AB85: =Z85 -> 357000 | AC85: =IF(AB85-S85<0,"YES","NO") -> YES | AD85: =IF(AC85="NO",0,AB85-S85) -> -93000 | AE85: 0.08 | AF85: =AD85/(1+AE85) -> -86111.111 | AG85: =AF85*1.1 -> -94722.222
A86: 2026-03-25 20:17:03 | B86: 2026-03-25 20:22:31 | C86: 2026-03-26 08:34:55 | D86: 2026-03-26 09:42:43 | E86: 2026-03-26 10:18:32 | F86: 2026-03-26 10:47:31 | G86: shopee_v2 | H86: physical | I86: GIFT-CHENANDAM | J86: [HÀNG TẶNG KHÔNG BÁN] Chén ăn dặm Zott Monte đáng yêu (màu ngẫu nhiên) - HÀNG TẶNG KHÔNG BÁN | K86: merchant | L86: VND | M86: Giao hàng thành công | N86: ODVN2603252239F876 | O86: 26032545X8G1AK | P86: 20 | Q86: 14x11x14 | R86: 1 | S86: 0 | T86: 0 | U86: 0 | V86: 0 | W86: 0 | X86: 0 | Y86: 0 | Z86: 0 | AA86: 8 | AB86: =Z86 -> 0 | AC86: =IF(AB86-S86<0,"YES","NO") -> NO | AD86: =IF(AC86="NO",0,AB86-S86) -> 0 | AE86: 0.08 | AF86: =AD86/(1+AE86) -> 0 | AG86: =AF86*1.1 -> 0
A87: 2026-03-25 20:17:03 | B87: 2026-03-25 20:22:31 | C87: 2026-03-26 08:34:55 | D87: 2026-03-26 09:42:43 | E87: 2026-03-26 10:18:32 | F87: 2026-03-26 10:47:31 | G87: shopee_v2 | H87: physical | I87: MON055GH04VAN | J87: Váng sữa Zott Monte vị Vani nhập khẩu từ ĐỨC, bé 6 tháng tuổi trở lên (vỉ - 55g x 4 hũ) từ Sữa tươi, KHÔNG chất bảo quản | K87: merchant | L87: VND | M87: Giao hàng thành công | N87: ODVN2603252239F876 | O87: 26032545X8G1AK | P87: 220 | R87: 6 | S87: 450000 | T87: 480000 | U87: 75000 | V87: 48000 | W87: 0 | X87: 146400 | Y87: 0 | Z87: 357000 | AA87: 8 | AB87: =Z87 -> 357000 | AC87: =IF(AB87-S87<0,"YES","NO") -> YES | AD87: =IF(AC87="NO",0,AB87-S87) -> -93000 | AE87: 0.08 | AF87: =AD87/(1+AE87) -> -86111.111 | AG87: =AF87*1.1 -> -94722.222
A88: 2026-03-25 19:33:17 | B88: 2026-03-25 19:38:25 | C88: 2026-03-26 08:35:07 | D88: 2026-03-26 09:35:54 | E88: 2026-03-26 09:53:21 | F88: 2026-03-29 10:53:47 | G88: shopee_v2 | H88: physical | I88: MON055GH04VAN | J88: Váng sữa Zott Monte vị Vani nhập khẩu từ ĐỨC, bé 6 tháng tuổi trở lên (vỉ - 55g x 4 hũ) từ Sữa tươi, KHÔNG chất bảo quản | K88: merchant | L88: VND | M88: Giao hàng thành công | N88: ODVN2603250178C1AF | O88: 26032543G06GAB | P88: 220 | R88: 6 | S88: 450000 | T88: 480000 | U88: 75000 | V88: 48000 | W88: 0 | X88: 164248.02 | Y88: 0 | Z88: 357000 | AA88: 8 | AB88: =Z88 -> 357000 | AC88: =IF(AB88-S88<0,"YES","NO") -> YES | AD88: =IF(AC88="NO",0,AB88-S88) -> -93000 | AE88: 0.08 | AF88: =AD88/(1+AE88) -> -86111.111 | AG88: =AF88*1.1 -> -94722.222
A89: 2026-03-25 15:49:17 | B89: 2026-03-25 15:54:45 | C89: 2026-03-25 16:57:30 | D89: 2026-03-26 11:47:27 | E89: 2026-03-26 12:35:48 | F89: 2026-03-29 13:53:15 | G89: shopee_v2 | H89: physical | I89: MON095MC04VAN | J89: Váng sữa uống Zott Monte Drink vị Vani nhập khẩu từ Đức, bé 6 tháng tuổi trở lên (vỉ - 95ml x 4 chai) từ Sữa tươi, KHÔNG chất bảo quản | K89: merchant | L89: VND | M89: Giao hàng thành công | N89: ODVN260325D67CC46B | O89: 2603253PXTT972 | P89: 380 | R89: 3 | S89: 198000 | T89: 210000 | U89: 35000.01 | V89: 21000 | W89: 0 | X89: 68880.99 | Y89: 0 | Z89: 153999.99 | AA89: 8 | AB89: =Z89 -> 153999.99 | AC89: =IF(AB89-S89<0,"YES","NO") -> YES | AD89: =IF(AC89="NO",0,AB89-S89) -> -44000.01 | AE89: 0.08 | AF89: =AD89/(1+AE89) -> -40740.75 | AG89: =AF89*1.1 -> -44814.825
A90: 2026-03-25 15:03:45 | B90: 2026-03-25 22:04:43 | C90: 2026-03-26 08:43:41 | D90: 2026-03-26 09:51:06 | E90: 2026-03-26 10:21:19 | F90: 2026-03-26 19:23:30 | G90: shopee_v2 | H90: gift | I90: GIFT-YEMANDAM | J90: [HÀNG TẶNG KHÔNG BÁN] Yếm ăn dặm cho bé | K90: merchant | L90: VND | M90: Giao hàng thành công | N90: ODVN2603253A0FE118 | O90: 2603253ME1ACGX | P90: 100 | Q90: 5x2x5 | R90: 1 | S90: 0 | T90: 0 | U90: 0 | V90: 0 | W90: 0 | X90: 0 | Y90: 0 | Z90: 0 | AA90: 8 | AB90: =Z90 -> 0 | AC90: =IF(AB90-S90<0,"YES","NO") -> NO | AD90: =IF(AC90="NO",0,AB90-S90) -> 0 | AE90: 0.08 | AF90: =AD90/(1+AE90) -> 0 | AG90: =AF90*1.1 -> 0
A91: 2026-03-25 15:03:45 | B91: 2026-03-25 22:04:43 | C91: 2026-03-26 08:43:41 | D91: 2026-03-26 09:51:06 | E91: 2026-03-26 10:21:19 | F91: 2026-03-26 19:23:30 | G91: shopee_v2 | H91: physical | I91: MON055GH04SCO | J91: Váng sữa Zott Monte vị Socola nhập khẩu từ Đức, bé 6 tháng tuổi trở lên (vỉ - 55g x 4 hũ) từ Sữa tươi, KHÔNG chất bảo quản | K91: merchant | L91: VND | M91: Giao hàng thành công | N91: ODVN2603253A0FE118 | O91: 2603253ME1ACGX | P91: 220 | R91: 6 | S91: 450000 | T91: 480000 | U91: 79999.98 | V91: 48000 | W91: 0 | X91: 168001.02 | Y91: 0 | Z91: 352000.02 | AA91: 8 | AB91: =Z91 -> 352000.02 | AC91: =IF(AB91-S91<0,"YES","NO") -> YES | AD91: =IF(AC91="NO",0,AB91-S91) -> -97999.98 | AE91: 0.08 | AF91: =AD91/(1+AE91) -> -90740.722 | AG91: =AF91*1.1 -> -99814.794
A92: 2026-03-25 14:38:32 | B92: 2026-03-25 14:39:45 | C92: 2026-03-25 14:54:24 | D92: 2026-03-25 15:34:55 | E92: 2026-03-25 15:58:28 | F92: 2026-03-28 16:15:31 | G92: shopee_v2 | H92: gift | I92: GIFT-YEMANDAM | J92: [HÀNG TẶNG KHÔNG BÁN] Yếm ăn dặm cho bé | K92: merchant | L92: VND | M92: Giao hàng thành công | N92: ODVN260325F1F2D06F | O92: 2603253K0XDSMN | P92: 100 | Q92: 5x2x5 | R92: 1 | S92: 0 | T92: 0 | U92: 0 | V92: 0 | W92: 0 | X92: 0 | Y92: 0 | Z92: 0 | AA92: 8 | AB92: =Z92 -> 0 | AC92: =IF(AB92-S92<0,"YES","NO") -> NO | AD92: =IF(AC92="NO",0,AB92-S92) -> 0 | AE92: 0.08 | AF92: =AD92/(1+AE92) -> 0 | AG92: =AF92*1.1 -> 0
A93: 2026-03-25 14:38:32 | B93: 2026-03-25 14:39:45 | C93: 2026-03-25 14:54:24 | D93: 2026-03-25 15:34:55 | E93: 2026-03-25 15:58:28 | F93: 2026-03-28 16:15:31 | G93: shopee_v2 | H93: physical | I93: MON055GH04VAN | J93: Váng sữa Zott Monte vị Vani nhập khẩu từ ĐỨC, bé 6 tháng tuổi trở lên (vỉ - 55g x 4 hũ) từ Sữa tươi, KHÔNG chất bảo quản | K93: merchant | L93: VND | M93: Giao hàng thành công | N93: ODVN260325F1F2D06F | O93: 2603253K0XDSMN | P93: 220 | R93: 2 | S93: 150000 | T93: 160000 | U93: 20000 | V93: 16000 | W93: 0 | X93: 38600 | Y93: 0 | Z93: 124000 | AA93: 8 | AB93: =Z93 -> 124000 | AC93: =IF(AB93-S93<0,"YES","NO") -> YES | AD93: =IF(AC93="NO",0,AB93-S93) -> -26000 | AE93: 0.08 | AF93: =AD93/(1+AE93) -> -24074.074 | AG93: =AF93*1.1 -> -26481.481
A94: 2026-03-25 14:37:50 | B94: 2026-03-25 14:43:08 | C94: 2026-03-25 14:54:30 | D94: 2026-03-25 15:03:40 | E94: 2026-03-25 15:14:26 | F94: 2026-03-28 16:23:41 | G94: shopee_v2 | H94: gift | I94: GIFT-YEMANDAM | J94: [HÀNG TẶNG KHÔNG BÁN] Yếm ăn dặm cho bé | K94: merchant | L94: VND | M94: Giao hàng thành công | N94: ODVN26032536E4C0B8 | O94: 2603253JY2DK5V | P94: 100 | Q94: 5x2x5 | R94: 1 | S94: 0 | T94: 0 | U94: 0 | V94: 0 | W94: 0 | X94: 0 | Y94: 0 | Z94: 0 | AA94: 8 | AB94: =Z94 -> 0 | AC94: =IF(AB94-S94<0,"YES","NO") -> NO | AD94: =IF(AC94="NO",0,AB94-S94) -> 0 | AE94: 0.08 | AF94: =AD94/(1+AE94) -> 0 | AG94: =AF94*1.1 -> 0
A95: 2026-03-25 14:37:50 | B95: 2026-03-25 14:43:08 | C95: 2026-03-25 14:54:30 | D95: 2026-03-25 15:03:40 | E95: 2026-03-25 15:14:26 | F95: 2026-03-28 16:23:41 | G95: shopee_v2 | H95: physical | I95: MON055GH04VAN | J95: Váng sữa Zott Monte vị Vani nhập khẩu từ ĐỨC, bé 6 tháng tuổi trở lên (vỉ - 55g x 4 hũ) từ Sữa tươi, KHÔNG chất bảo quản | K95: merchant | L95: VND | M95: Giao hàng thành công | N95: ODVN26032536E4C0B8 | O95: 2603253JY2DK5V | P95: 220 | R95: 3 | S95: 225000 | T95: 240000 | U95: 35000.01 | V95: 24000 | W95: 0 | X95: 62150.01 | Y95: 0 | Z95: 180999.99 | AA95: 8 | AB95: =Z95 -> 180999.99 | AC95: =IF(AB95-S95<0,"YES","NO") -> YES | AD95: =IF(AC95="NO",0,AB95-S95) -> -44000.01 | AE95: 0.08 | AF95: =AD95/(1+AE95) -> -40740.75 | AG95: =AF95*1.1 -> -44814.825
A96: 2026-03-25 14:25:17 | B96: 2026-03-25 14:30:51 | C96: 2026-03-25 14:54:18 | D96: 2026-03-25 15:09:41 | E96: 2026-03-25 15:23:06 | F96: 2026-03-28 16:07:24 | G96: shopee_v2 | H96: gift | I96: GIFT-BOBONGRO | J96: [HÀNG TẶNG KHÔNG BÁN] Bộ đồ chơi bóng rổ đáng yêu (hình ngẫu nhiên) | K96: merchant | L96: VND | M96: Giao hàng thành công | N96: ODVN2603253B8E449F | O96: 2603253J97ARJE | P96: 20000 | Q96: 5x3x5 | R96: 1 | S96: 0 | T96: 0 | U96: 0 | V96: 0 | W96: 0 | X96: 0 | Y96: 0 | Z96: 0 | AA96: 8 | AB96: =Z96 -> 0 | AC96: =IF(AB96-S96<0,"YES","NO") -> NO | AD96: =IF(AC96="NO",0,AB96-S96) -> 0 | AE96: 0.08 | AF96: =AD96/(1+AE96) -> 0 | AG96: =AF96*1.1 -> 0
A97: 2026-03-25 14:25:17 | B97: 2026-03-25 14:30:51 | C97: 2026-03-25 14:54:18 | D97: 2026-03-25 15:09:41 | E97: 2026-03-25 15:23:06 | F97: 2026-03-28 16:07:24 | G97: shopee_v2 | H97: gift | I97: GIFT-YEMANDAM | J97: [HÀNG TẶNG KHÔNG BÁN] Yếm ăn dặm cho bé | K97: merchant | L97: VND | M97: Giao hàng thành công | N97: ODVN2603253B8E449F | O97: 2603253J97ARJE | P97: 100 | Q97: 5x2x5 | R97: 1 | S97: 0 | T97: 0 | U97: 0 | V97: 0 | W97: 0 | X97: 0 | Y97: 0 | Z97: 0 | AA97: 8 | AB97: =Z97 -> 0 | AC97: =IF(AB97-S97<0,"YES","NO") -> NO | AD97: =IF(AC97="NO",0,AB97-S97) -> 0 | AE97: 0.08 | AF97: =AD97/(1+AE97) -> 0 | AG97: =AF97*1.1 -> 0
A98: 2026-03-25 14:25:17 | B98: 2026-03-25 14:30:51 | C98: 2026-03-25 14:54:18 | D98: 2026-03-25 15:09:41 | E98: 2026-03-25 15:23:06 | F98: 2026-03-28 16:07:24 | G98: shopee_v2 | H98: physical | I98: MNF055GC04STB | J98: [Giao Hỏa Tốc] Phô mai tươi Montinis vị Dâu nhập ĐỨC (vỉ - 55g x 4 hũ) | K98: merchant | L98: VND | M98: Giao hàng thành công | N98: ODVN2603253B8E449F | O98: 2603253J97ARJE | P98: 220 | Q98: 10x5x15 | R98: 1 | S98: 59000 | T98: 70000 | U98: 12173 | V98: 7000 | W98: 0 | X98: 20305 | Y98: 0 | Z98: 50827 | AA98: 8 | AB98: =Z98 -> 50827 | AC98: =IF(AB98-S98<0,"YES","NO") -> YES | AD98: =IF(AC98="NO",0,AB98-S98) -> -8173 | AE98: 0.08 | AF98: =AD98/(1+AE98) -> -7567.5926 | AG98: =AF98*1.1 -> -8324.3519
A99: 2026-03-25 14:25:17 | B99: 2026-03-25 14:30:51 | C99: 2026-03-25 14:54:18 | D99: 2026-03-25 15:09:41 | E99: 2026-03-25 15:23:06 | F99: 2026-03-28 16:07:24 | G99: shopee_v2 | H99: physical | I99: MNF055GC04VAN | J99: [Giao Hỏa Tốc] Phô mai tươi Montinis vị Vani nhập ĐỨC (vỉ - 55g x 4 hũ) | K99: merchant | L99: VND | M99: Giao hàng thành công | N99: ODVN2603253B8E449F | O99: 2603253J97ARJE | P99: 220 | Q99: 10x10x15 | R99: 1 | S99: 59000 | T99: 70000 | U99: 12173 | V99: 7000 | W99: 0 | X99: 20305 | Y99: 0 | Z99: 50827 | AA99: 8 | AB99: =Z99 -> 50827 | AC99: =IF(AB99-S99<0,"YES","NO") -> YES | AD99: =IF(AC99="NO",0,AB99-S99) -> -8173 | AE99: 0.08 | AF99: =AD99/(1+AE99) -> -7567.5926 | AG99: =AF99*1.1 -> -8324.3519
A100: 2026-03-25 14:25:17 | B100: 2026-03-25 14:30:51 | C100: 2026-03-25 14:54:18 | D100: 2026-03-25 15:09:41 | E100: 2026-03-25 15:23:06 | F100: 2026-03-28 16:07:24 | G100: shopee_v2 | H100: physical | I100: MON055GH04VAN | J100: Váng sữa Zott Monte vị Vani nhập khẩu từ ĐỨC, bé 6 tháng tuổi trở lên (vỉ - 55g x 4 hũ) từ Sữa tươi, KHÔNG chất bảo quản | K100: merchant | L100: VND | M100: Giao hàng thành công | N100: ODVN2603253B8E449F | O100: 2603253J97ARJE | P100: 220 | R100: 2 | S100: 150000 | T100: 160000 | U100: 27827 | V100: 16000 | W100: 0 | X100: 46415 | Y100: 0 | Z100: 116173 | AA100: 8 | AB100: =Z100 -> 116173 | AC100: =IF(AB100-S100<0,"YES","NO") -> YES | AD100: =IF(AC100="NO",0,AB100-S100) -> -33827 | AE100: 0.08 | AF100: =AD100/(1+AE100) -> -31321.296 | AG100: =AF100*1.1 -> -34453.426
...

Sheet Sheet2
A1: 260225K8FCCABB
A2: 260225K8FCCABB
A3: 260225K8AJV03Q
A4: 2602097U64GD5J
A5: 260201J2PCP562 | C5: MNF055GC04STB | E5: MNF055GC04VAN | H5: MON055GH04VAN

Sheet Check
A1: Mã đơn hàng | B1: NMV | C1: Shop | D1: Sàn trả | E1: CL | J1: 260305C91P1H8F | L1: MON055GH04CLA | N1: MON055GH04VAN
A2: 260224HT0R6DHC | B2: 357000 | C2: =VLOOKUP(A2,Defaut!O:O,2,0) -> #REF! | D2: =SUMIF([2]Sheet2!$C:$C,A2,[2]Sheet2!$M:$M) -> 357000 | E2: =D2-B2 -> 0 | J2: 260305B5VG29N9
A3: 260224HTBBPE5M | B3: 357000 | C3: =VLOOKUP(A3,Defaut!O:O,2,0) -> #REF! | D3: =SUMIF([2]Sheet2!$C:$C,A3,[2]Sheet2!$M:$M) -> 357000 | E3: =D3-B3 -> 0
A4: 260225M6TX49N2 | B4: 357000 | C4: =VLOOKUP(A4,Defaut!O:O,2,0) -> #REF! | D4: =SUMIF([2]Sheet2!$C:$C,A4,[2]Sheet2!$M:$M) -> 357000 | E4: =D4-B4 -> 0
A5: 260225M7FK0HYH | B5: 355999.98 | C5: =VLOOKUP(A5,Defaut!O:O,2,0) -> #REF! | D5: =SUMIF([2]Sheet2!$C:$C,A5,[2]Sheet2!$M:$M) -> 356000 | E5: =D5-B5 -> 0.02
A6: 260225MB8THV5Y | B6: 357000 | C6: =VLOOKUP(A6,Defaut!O:O,2,0) -> #REF! | D6: =SUMIF([2]Sheet2!$C:$C,A6,[2]Sheet2!$M:$M) -> 357000 | E6: =D6-B6 -> 0
A7: 260225N63PHKJU | B7: 180999.99 | C7: =VLOOKUP(A7,Defaut!O:O,2,0) -> #REF! | D7: =SUMIF([2]Sheet2!$C:$C,A7,[2]Sheet2!$M:$M) -> 181000 | E7: =D7-B7 -> 0.01
A8: 260226PDWCP2RF | B8: 271999.99 | C8: =VLOOKUP(A8,Defaut!O:O,2,0) -> #REF! | D8: =SUMIF([2]Sheet2!$C:$C,A8,[2]Sheet2!$M:$M) -> 272000 | E8: =D8-B8 -> 0.01
A9: 260226PJB693HT | B9: 124000 | C9: =VLOOKUP(A9,Defaut!O:O,2,0) -> #REF! | D9: =SUMIF([2]Sheet2!$C:$C,A9,[2]Sheet2!$M:$M) -> 124000 | E9: =D9-B9 -> 0
A10: 260226PKM7ESQK | B10: 180999.99 | C10: =VLOOKUP(A10,Defaut!O:O,2,0) -> #REF! | D10: =SUMIF([2]Sheet2!$C:$C,A10,[2]Sheet2!$M:$M) -> 181000 | E10: =D10-B10 -> 0.01
A11: 260226PV4MXSEJ | B11: 180999.99 | C11: =VLOOKUP(A11,Defaut!O:O,2,0) -> #REF! | D11: =SUMIF([2]Sheet2!$C:$C,A11,[2]Sheet2!$M:$M) -> 181000 | E11: =D11-B11 -> 0.01
A12: 260226Q23XKAYU | B12: 140499.99 | C12: =VLOOKUP(A12,Defaut!O:O,2,0) -> #REF! | D12: =SUMIF([2]Sheet2!$C:$C,A12,[2]Sheet2!$M:$M) -> 140500 | E12: =D12-B12 -> 0.01
A13: 260226Q2BPJ8UA | B13: 140499.99 | C13: =VLOOKUP(A13,Defaut!O:O,2,0) -> #REF! | D13: =SUMIF([2]Sheet2!$C:$C,A13,[2]Sheet2!$M:$M) -> 140500 | E13: =D13-B13 -> 0.01
A14: 260226Q2H6252U | B14: 124000 | C14: =VLOOKUP(A14,Defaut!O:O,2,0) -> #REF! | D14: =SUMIF([2]Sheet2!$C:$C,A14,[2]Sheet2!$M:$M) -> 124000 | E14: =D14-B14 -> 0
... A576: 260331JEART4VD | B576: 124000 | C576: =VLOOKUP(A576,Defaut!O:O,2,0) -> #REF! | D576: =SUMIF([2]Sheet2!$C:$C,A576,[2]Sheet2!$M:$M) -> 124000 | E576: =D576-B576 -> 0
A577: 523586247432246 | B577: 159999.99 | C577: =VLOOKUP(A577,Defaut!O:O,2,0) -> #REF! | D577: =VLOOKUP(A577,[1]Sheet2!$F:$G,2,0) -> 160000 | E577: =D577-B577 -> 0.01
A578: 525836549136523 | B578: 552000 | C578: =VLOOKUP(A578,Defaut!O:O,2,0) -> #REF! | D578: =VLOOKUP(A578,[1]Sheet2!$F:$G,2,0) -> 552000 | E578: =D578-B578 -> 0
A579: 525992773048327 | B579: 390000 | C579: =VLOOKUP(A579,Defaut!O:O,2,0) -> #REF! | D579: =VLOOKUP(A579,[1]Sheet2!$F:$G,2,0) -> 390000 | E579: =D579-B579 -> 0
A580: 582783452440463185 | B580: 65000 | C580: =VLOOKUP(A580,Defaut!O:O,2,0) -> #REF! | D580: =SUMIF('[3]Order details'!$A:$A,A580,'[3]Order details'!$G:$G) -> 65000 | E580: =D580-B580 -> 0
A581: 582820641108755993 | B581: 134000 | C581: =VLOOKUP(A581,Defaut!O:O,2,0) -> #REF! | D581: =SUMIF('[3]Order details'!$A:$A,A581,'[3]Order details'!$G:$G) -> 134000 | E581: =D581-B581 -> 0
A582: 582895129806079725 | B582: 260000 | C582: =VLOOKUP(A582,Defaut!O:O,2,0) -> #REF! | D582: =SUMIF('[3]Order details'!$A:$A,A582,'[3]Order details'!$G:$G) -> 260000 | E582: =D582-B582 -> 0
A583: 583006645176665976 | B583: 130000 | C583: =VLOOKUP(A583,Defaut!O:O,2,0) -> #REF! | D583: =SUMIF('[3]Order details'!$A:$A,A583,'[3]Order details'!$G:$G) -> 130000 | E583: =D583-B583 -> 0
A584: 583041928825111727 | B584: 384000 | C584: =VLOOKUP(A584,Defaut!O:O,2,0) -> #REF! | D584: =SUMIF('[3]Order details'!$A:$A,A584,'[3]Order details'!$G:$G) -> 384000 | E584: =D584-B584 -> 0
A585: 583087700030621209 | B585: 390000 | C585: =VLOOKUP(A585,Defaut!O:O,2,0) -> #REF! | D585: =SUMIF('[3]Order details'!$A:$A,A585,'[3]Order details'!$G:$G) -> 390000 | E585: =D585-B585 -> 0
